<typedefs>
  <typedef name="String"
    embed="var"
    ponytypein="String"
    ponytypeinconv=".cstring()"
    ponytypeout="String"
    structtype="Pointer[U8]"
    structdef="Pointer[U8]"
    argtype="Pointer[U8] tag"
    rvtype="Pointer[U8]">
    <ponytypeconvout>
      <prefixs>
        <prefix>var pcstring: Pointer[U8] = </prefix>
      </prefixs>
      <suffixes>
        <suffix>let p: String iso = String.from_cstring(pcstring).clone()</suffix>
        <suffix>consume p</suffix>
      </suffixes>
    </ponytypeconvout>
  </typedef>

  <typedef name="Array[String]"
    embed="var"
    ponytypein="Pointer[Pointer[U8]] tag"
    ponytypeinconv=""
    ponytypeout="Pointer[Pointer[U8]]"
    structtype="Pointer[Pointer[U8]]"
    structdef="Pointer[Pointer[U8]]"
    argtype="Pointer[Pointer[U8]] tag"
    rvtype="Pointer[Pointer[U8]]"/>

  <typedef name="X509objectst"
    embed="embed"
    ponytypein="X509Object tag"
    ponytypeinconv=""
    ponytypeout="X509Object"
    structtype="X509Object"
    structdef="X509Object"
    argtype="X509Object tag"
    rvtype="X509Object"/>

  <typedef name="X509POLICYLEVELst"
    embed="embed"
    ponytypein="X509POLICYLEVELst tag"
    ponytypeinconv=""
    ponytypeout="X509POLICYLEVELst"
    structtype="X509POLICYLEVELst"
    structdef="X509POLICYLEVELst"
    argtype="X509POLICYLEVELst tag"
    rvtype="X509POLICYLEVELst"/>

  <typedef name="Ssldanest"
    embed="embed"
    ponytypein="Ssldanest tag"
    ponytypeinconv=""
    ponytypeout="Ssldanest"
    structtype="Ssldanest"
    structdef="Ssldanest"
    argtype="Ssldanest tag"
    rvtype="Ssldanest"/>

  <typedef name="CMSSignerInfost"
    embed="embed"
    ponytypein="CMSSignerInfost tag"
    ponytypeinconv=""
    ponytypeout="CMSSignerInfost"
    structtype="CMSSignerInfost"
    structdef="CMSSignerInfost"
    argtype="CMSSignerInfost tag"
    rvtype="CMSSignerInfost"/>

  <typedef name="StackstPKCS12SAFEBAG"
    embed="embed"
    ponytypein="StackstPKCS12SAFEBAG tag"
    ponytypeinconv=""
    ponytypeout="StackstPKCS12SAFEBAG"
    structtype="StackstPKCS12SAFEBAG"
    structdef="StackstPKCS12SAFEBAG"
    argtype="StackstPKCS12SAFEBAG tag"
    rvtype="StackstPKCS12SAFEBAG"/>

  <typedef name="Sctst"
    embed="embed"
    ponytypein="Sctst tag"
    ponytypeinconv=""
    ponytypeout="Sctst"
    structtype="Sctst"
    structdef="Sctst"
    argtype="Sctst tag"
    rvtype="Sctst"/>

  <typedef name="Bngencbst"
    embed="embed"
    ponytypein="Bngencbst tag"
    ponytypeinconv=""
    ponytypeout="Bngencbst"
    structtype="Bngencbst"
    structdef="Bngencbst"
    argtype="Bngencbst tag"
    rvtype="Bngencbst"/>

  <typedef name="Stackst"
    embed="embed"
    ponytypein="Stackst tag"
    ponytypeinconv=""
    ponytypeout="Stackst"
    structtype="Stackst"
    structdef="Stackst"
    argtype="Stackst tag"
    rvtype="Stackst"/>

  <typedef name="Ocspresponsest"
    embed="embed"
    ponytypein="Ocspresponsest tag"
    ponytypeinconv=""
    ponytypeout="Ocspresponsest"
    structtype="Ocspresponsest"
    structdef="Ocspresponsest"
    argtype="Ocspresponsest tag"
    rvtype="Ocspresponsest"/>

  <typedef name="Ocspreqinfost"
    embed="embed"
    ponytypein="Ocspreqinfost tag"
    ponytypeinconv=""
    ponytypeout="Ocspreqinfost"
    structtype="Ocspreqinfost"
    structdef="Ocspreqinfost"
    argtype="Ocspreqinfost tag"
    rvtype="Ocspreqinfost"/>

  <typedef name="X509crlinfost"
    embed="embed"
    ponytypein="X509crlinfost tag"
    ponytypeinconv=""
    ponytypeout="X509crlinfost"
    structtype="X509crlinfost"
    structdef="X509crlinfost"
    argtype="X509crlinfost tag"
    rvtype="X509crlinfost"/>

  <typedef name="Evppkeyctxst"
    embed="embed"
    ponytypein="Evppkeyctxst tag"
    ponytypeinconv=""
    ponytypeout="Evppkeyctxst"
    structtype="Evppkeyctxst"
    structdef="Evppkeyctxst"
    argtype="Evppkeyctxst tag"
    rvtype="Evppkeyctxst"/>

  <typedef name="PKCS12SAFEBAGst"
    embed="embed"
    ponytypein="PKCS12SAFEBAGst tag"
    ponytypeinconv=""
    ponytypeout="PKCS12SAFEBAGst"
    structtype="PKCS12SAFEBAGst"
    structdef="PKCS12SAFEBAGst"
    argtype="PKCS12SAFEBAGst tag"
    rvtype="PKCS12SAFEBAGst"/>

  <typedef name="Hostent"
    embed="embed"
    ponytypein="Hostent tag"
    ponytypeinconv=""
    ponytypeout="Hostent"
    structtype="Hostent"
    structdef="Hostent"
    argtype="Hostent tag"
    rvtype="Hostent"/>

  <typedef name="I64"
    embed="var"
    ponytypein="I64"
    ponytypeinconv=""
    ponytypeout="I64"
    structtype="I64"
    structdef="I64(0)"
    argtype="I64"
    rvtype="I64"/>

  <typedef name="Pkcs7issuerandserialst"
    embed="embed"
    ponytypein="Pkcs7issuerandserialst tag"
    ponytypeinconv=""
    ponytypeout="Pkcs7issuerandserialst"
    structtype="Pkcs7issuerandserialst"
    structdef="Pkcs7issuerandserialst"
    argtype="Pkcs7issuerandserialst tag"
    rvtype="Pkcs7issuerandserialst"/>

  <typedef name="Bioaddrinfost"
    embed="embed"
    ponytypein="Bioaddrinfost tag"
    ponytypeinconv=""
    ponytypeout="Bioaddrinfost"
    structtype="Bioaddrinfost"
    structdef="Bioaddrinfost"
    argtype="Bioaddrinfost tag"
    rvtype="Bioaddrinfost"/>

  <typedef name="RIPEMD160statest"
    embed="embed"
    ponytypein="RIPEMD160statest tag"
    ponytypeinconv=""
    ponytypeout="RIPEMD160statest"
    structtype="RIPEMD160statest"
    structdef="RIPEMD160statest"
    argtype="RIPEMD160statest tag"
    rvtype="RIPEMD160statest"/>

  <typedef name="Ocspcertstatusst"
    embed="embed"
    ponytypein="Ocspcertstatusst tag"
    ponytypeinconv=""
    ponytypeout="Ocspcertstatusst"
    structtype="Ocspcertstatusst"
    structdef="Ocspcertstatusst"
    argtype="Ocspcertstatusst tag"
    rvtype="Ocspcertstatusst"/>

  <typedef name="StackstGENERALNAMES"
    embed="embed"
    ponytypein="StackstGENERALNAMES tag"
    ponytypeinconv=""
    ponytypeout="StackstGENERALNAMES"
    structtype="StackstGENERALNAMES"
    structdef="StackstGENERALNAMES"
    argtype="StackstGENERALNAMES tag"
    rvtype="StackstGENERALNAMES"/>

  <typedef name="StackstSXNETID"
    embed="embed"
    ponytypein="StackstSXNETID tag"
    ponytypeinconv=""
    ponytypeout="StackstSXNETID"
    structtype="StackstSXNETID"
    structdef="StackstSXNETID"
    argtype="StackstSXNETID tag"
    rvtype="StackstSXNETID"/>

  <typedef name="StackstUISTRING"
    embed="embed"
    ponytypein="StackstUISTRING tag"
    ponytypeinconv=""
    ponytypeout="StackstUISTRING"
    structtype="StackstUISTRING"
    structdef="StackstUISTRING"
    argtype="StackstUISTRING tag"
    rvtype="StackstUISTRING"/>

  <typedef name="Sslconfctxst"
    embed="embed"
    ponytypein="Sslconfctxst tag"
    ponytypeinconv=""
    ponytypeout="Sslconfctxst"
    structtype="Sslconfctxst"
    structdef="Sslconfctxst"
    argtype="Sslconfctxst tag"
    rvtype="Sslconfctxst"/>

  <typedef name="Asyncwaitctxst"
    embed="embed"
    ponytypein="Asyncwaitctxst tag"
    ponytypeinconv=""
    ponytypeout="Asyncwaitctxst"
    structtype="Asyncwaitctxst"
    structdef="Asyncwaitctxst"
    argtype="Asyncwaitctxst tag"
    rvtype="Asyncwaitctxst"/>

  <typedef name="StackstSSLCOMP"
    embed="embed"
    ponytypein="StackstSSLCOMP tag"
    ponytypeinconv=""
    ponytypeout="StackstSSLCOMP"
    structtype="StackstSSLCOMP"
    structdef="StackstSSLCOMP"
    argtype="StackstSSLCOMP tag"
    rvtype="StackstSSLCOMP"/>

  <typedef name="StackstPOLICYINFO"
    embed="embed"
    ponytypein="StackstPOLICYINFO tag"
    ponytypeinconv=""
    ponytypeout="StackstPOLICYINFO"
    structtype="StackstPOLICYINFO"
    structdef="StackstPOLICYINFO"
    argtype="StackstPOLICYINFO tag"
    rvtype="StackstPOLICYINFO"/>

  <typedef name="Pkcs7enccontentst"
    embed="embed"
    ponytypein="Pkcs7enccontentst tag"
    ponytypeinconv=""
    ponytypeout="Pkcs7enccontentst"
    structtype="Pkcs7enccontentst"
    structdef="Pkcs7enccontentst"
    argtype="Pkcs7enccontentst tag"
    rvtype="Pkcs7enccontentst"/>

  <typedef name="Randmethst"
    embed="embed"
    ponytypein="Randmethst tag"
    ponytypeinconv=""
    ponytypeout="Randmethst"
    structtype="Randmethst"
    structdef="Randmethst"
    argtype="Randmethst tag"
    rvtype="Randmethst"/>

  <typedef name="X509storectxst"
    embed="embed"
    ponytypein="X509storectxst tag"
    ponytypeinconv=""
    ponytypeout="X509storectxst"
    structtype="X509storectxst"
    structdef="X509storectxst"
    argtype="X509storectxst tag"
    rvtype="X509storectxst"/>

  <typedef name="Ecgroupst"
    embed="embed"
    ponytypein="Ecgroupst tag"
    ponytypeinconv=""
    ponytypeout="Ecgroupst"
    structtype="Ecgroupst"
    structdef="Ecgroupst"
    argtype="Ecgroupst tag"
    rvtype="Ecgroupst"/>

  <typedef name="StackstX509V3EXTMETHOD"
    embed="embed"
    ponytypein="StackstX509V3EXTMETHOD tag"
    ponytypeinconv=""
    ponytypeout="StackstX509V3EXTMETHOD"
    structtype="StackstX509V3EXTMETHOD"
    structdef="StackstX509V3EXTMETHOD"
    argtype="StackstX509V3EXTMETHOD tag"
    rvtype="StackstX509V3EXTMETHOD"/>

  <typedef name="MD4statest"
    embed="embed"
    ponytypein="MD4statest tag"
    ponytypeinconv=""
    ponytypeout="MD4statest"
    structtype="MD4statest"
    structdef="MD4statest"
    argtype="MD4statest tag"
    rvtype="MD4statest"/>

  <typedef name="Rsamethst"
    embed="embed"
    ponytypein="Rsamethst tag"
    ponytypeinconv=""
    ponytypeout="Rsamethst"
    structtype="Rsamethst"
    structdef="Rsamethst"
    argtype="Rsamethst tag"
    rvtype="Rsamethst"/>

  <typedef name="AdmissionSyntaxst"
    embed="embed"
    ponytypein="AdmissionSyntaxst tag"
    ponytypeinconv=""
    ponytypeout="AdmissionSyntaxst"
    structtype="AdmissionSyntaxst"
    structdef="AdmissionSyntaxst"
    argtype="AdmissionSyntaxst tag"
    rvtype="AdmissionSyntaxst"/>

  <typedef name="CMSRevocationInfoChoicest"
    embed="embed"
    ponytypein="CMSRevocationInfoChoicest tag"
    ponytypeinconv=""
    ponytypeout="CMSRevocationInfoChoicest"
    structtype="CMSRevocationInfoChoicest"
    structdef="CMSRevocationInfoChoicest"
    argtype="CMSRevocationInfoChoicest tag"
    rvtype="CMSRevocationInfoChoicest"/>

  <typedef name="StackstPKCS7SIGNERINFO"
    embed="embed"
    ponytypein="StackstPKCS7SIGNERINFO tag"
    ponytypeinconv=""
    ponytypeout="StackstPKCS7SIGNERINFO"
    structtype="StackstPKCS7SIGNERINFO"
    structdef="StackstPKCS7SIGNERINFO"
    argtype="StackstPKCS7SIGNERINFO tag"
    rvtype="StackstPKCS7SIGNERINFO"/>

  <typedef name="Osslstoreloaderst"
    embed="embed"
    ponytypein="Osslstoreloaderst tag"
    ponytypeinconv=""
    ponytypeout="Osslstoreloaderst"
    structtype="Osslstoreloaderst"
    structdef="Osslstoreloaderst"
    argtype="Osslstoreloaderst tag"
    rvtype="Osslstoreloaderst"/>

  <typedef name="Uistringst"
    embed="embed"
    ponytypein="Uistringst tag"
    ponytypeinconv=""
    ponytypeout="Uistringst"
    structtype="Uistringst"
    structdef="Uistringst"
    argtype="Uistringst tag"
    rvtype="Uistringst"/>

  <typedef name="Pkcs7signedst"
    embed="embed"
    ponytypein="Pkcs7signedst tag"
    ponytypeinconv=""
    ponytypeout="Pkcs7signedst"
    structtype="Pkcs7signedst"
    structdef="Pkcs7signedst"
    argtype="Pkcs7signedst tag"
    rvtype="Pkcs7signedst"/>

  <typedef name="NamingAuthorityst"
    embed="embed"
    ponytypein="NamingAuthorityst tag"
    ponytypeinconv=""
    ponytypeout="NamingAuthorityst"
    structtype="NamingAuthorityst"
    structdef="NamingAuthorityst"
    argtype="NamingAuthorityst tag"
    rvtype="NamingAuthorityst"/>

  <typedef name="CMSRecipientInfost"
    embed="embed"
    ponytypein="CMSRecipientInfost tag"
    ponytypeinconv=""
    ponytypeout="CMSRecipientInfost"
    structtype="CMSRecipientInfost"
    structdef="CMSRecipientInfost"
    argtype="CMSRecipientInfost tag"
    rvtype="CMSRecipientInfost"/>

  <typedef name="Rsapssparamsst"
    embed="embed"
    ponytypein="Rsapssparamsst tag"
    ponytypeinconv=""
    ponytypeout="Rsapssparamsst"
    structtype="Rsapssparamsst"
    structdef="Rsapssparamsst"
    argtype="Rsapssparamsst tag"
    rvtype="Rsapssparamsst"/>

  <typedef name="X509VERIFYPARAMst"
    embed="embed"
    ponytypein="X509VERIFYPARAMst tag"
    ponytypeinconv=""
    ponytypeout="X509VERIFYPARAMst"
    structtype="X509VERIFYPARAMst"
    structdef="X509VERIFYPARAMst"
    argtype="X509VERIFYPARAMst tag"
    rvtype="X509VERIFYPARAMst"/>

  <typedef name="StackstOPENSSLBLOCK"
    embed="embed"
    ponytypein="StackstOPENSSLBLOCK tag"
    ponytypeinconv=""
    ponytypeout="StackstOPENSSLBLOCK"
    structtype="StackstOPENSSLBLOCK"
    structdef="StackstOPENSSLBLOCK"
    argtype="StackstOPENSSLBLOCK tag"
    rvtype="StackstOPENSSLBLOCK"/>

  <typedef name="StackstSSLCIPHER"
    embed="embed"
    ponytypein="StackstSSLCIPHER tag"
    ponytypeinconv=""
    ponytypeout="StackstSSLCIPHER"
    structtype="StackstSSLCIPHER"
    structdef="StackstSSLCIPHER"
    argtype="StackstSSLCIPHER tag"
    rvtype="StackstSSLCIPHER"/>

  <typedef name="Ocspcertidst"
    embed="embed"
    ponytypein="Ocspcertidst tag"
    ponytypeinconv=""
    ponytypeout="Ocspcertidst"
    structtype="Ocspcertidst"
    structdef="Ocspcertidst"
    argtype="Ocspcertidst tag"
    rvtype="Ocspcertidst"/>

  <typedef name="Evpmdctxst"
    embed="embed"
    ponytypein="Evpmdctxst tag"
    ponytypeinconv=""
    ponytypeout="Evpmdctxst"
    structtype="Evpmdctxst"
    structdef="Evpmdctxst"
    argtype="Evpmdctxst tag"
    rvtype="Evpmdctxst"/>

  <typedef name="StackstOCSPSINGLERESP"
    embed="embed"
    ponytypein="StackstOCSPSINGLERESP tag"
    ponytypeinconv=""
    ponytypeout="StackstOCSPSINGLERESP"
    structtype="StackstOCSPSINGLERESP"
    structdef="StackstOCSPSINGLERESP"
    argtype="StackstOCSPSINGLERESP tag"
    rvtype="StackstOCSPSINGLERESP"/>

  <typedef name="StackstPOLICYMAPPING"
    embed="embed"
    ponytypein="StackstPOLICYMAPPING tag"
    ponytypeinconv=""
    ponytypeout="StackstPOLICYMAPPING"
    structtype="StackstPOLICYMAPPING"
    structdef="StackstPOLICYMAPPING"
    argtype="StackstPOLICYMAPPING tag"
    rvtype="StackstPOLICYMAPPING"/>

  <typedef name="F64"
    embed="var"
    ponytypein="F64"
    ponytypeinconv=""
    ponytypeout="F64"
    structtype="F64"
    structdef="F64(0)"
    argtype="F64"
    rvtype="F64"/>

  <typedef name="Ecpkparametersst"
    embed="embed"
    ponytypein="Ecpkparametersst tag"
    ponytypeinconv=""
    ponytypeout="Ecpkparametersst"
    structtype="Ecpkparametersst"
    structdef="Ecpkparametersst"
    argtype="Ecpkparametersst tag"
    rvtype="Ecpkparametersst"/>

  <typedef name="X509siginfost"
    embed="embed"
    ponytypein="X509siginfost tag"
    ponytypeinconv=""
    ponytypeout="X509siginfost"
    structtype="X509siginfost"
    structdef="X509siginfost"
    argtype="X509siginfost tag"
    rvtype="X509siginfost"/>

  <typedef name="I32"
    embed="var"
    ponytypein="I32"
    ponytypeinconv=""
    ponytypeout="I32"
    structtype="I32"
    structdef="I32(0)"
    argtype="I32"
    rvtype="I32"/>

  <typedef name="StackstIPAddressOrRange"
    embed="embed"
    ponytypein="StackstIPAddressOrRange tag"
    ponytypeinconv=""
    ponytypeout="StackstIPAddressOrRange"
    structtype="StackstIPAddressOrRange"
    structdef="StackstIPAddressOrRange"
    argtype="StackstIPAddressOrRange tag"
    rvtype="StackstIPAddressOrRange"/>

  <typedef name="Pointer[U32]"
    embed="var"
    ponytypein="Pointer[U32] tag"
    ponytypeinconv=""
    ponytypeout="Pointer[U32]"
    structtype="Pointer[U32]"
    structdef="Pointer[U32]"
    argtype="Pointer[U32] tag"
    rvtype="Pointer[U32]"/>

  <typedef name="Asn1stringtablest"
    embed="embed"
    ponytypein="Asn1stringtablest tag"
    ponytypeinconv=""
    ponytypeout="Asn1stringtablest"
    structtype="Asn1stringtablest"
    structdef="Asn1stringtablest"
    argtype="Asn1stringtablest tag"
    rvtype="Asn1stringtablest"/>

  <typedef name="X509valst"
    embed="embed"
    ponytypein="X509valst tag"
    ponytypeinconv=""
    ponytypeout="X509valst"
    structtype="X509valst"
    structdef="X509valst"
    argtype="X509valst tag"
    rvtype="X509valst"/>

  <typedef name="IOFILE"
    embed="embed"
    ponytypein="IOFILE tag"
    ponytypeinconv=""
    ponytypeout="IOFILE"
    structtype="IOFILE"
    structdef="IOFILE"
    argtype="IOFILE tag"
    rvtype="IOFILE"/>

  <typedef name="StackX509Object"
    embed="embed"
    ponytypein="StackX509Object tag"
    ponytypeinconv=""
    ponytypeout="StackX509Object"
    structtype="StackX509Object"
    structdef="StackX509Object"
    argtype="StackX509Object tag"
    rvtype="StackX509Object"/>

  <typedef name="X509purposest"
    embed="embed"
    ponytypein="X509purposest tag"
    ponytypeinconv=""
    ponytypeout="X509purposest"
    structtype="X509purposest"
    structdef="X509purposest"
    argtype="X509purposest tag"
    rvtype="X509purposest"/>

  <typedef name="ENGINECMDDEFNst"
    embed="embed"
    ponytypein="ENGINECMDDEFNst tag"
    ponytypeinconv=""
    ponytypeout="ENGINECMDDEFNst"
    structtype="ENGINECMDDEFNst"
    structdef="ENGINECMDDEFNst"
    argtype="ENGINECMDDEFNst tag"
    rvtype="ENGINECMDDEFNst"/>

  <typedef name="ASN1VALUEst"
    embed="embed"
    ponytypein="ASN1VALUEst tag"
    ponytypeinconv=""
    ponytypeout="ASN1VALUEst"
    structtype="ASN1VALUEst"
    structdef="ASN1VALUEst"
    argtype="ASN1VALUEst tag"
    rvtype="ASN1VALUEst"/>

  <typedef name="StackstX509ALGOR"
    embed="embed"
    ponytypein="StackstX509ALGOR tag"
    ponytypeinconv=""
    ponytypeout="StackstX509ALGOR"
    structtype="StackstX509ALGOR"
    structdef="StackstX509ALGOR"
    argtype="StackstX509ALGOR tag"
    rvtype="StackstX509ALGOR"/>

  <typedef name="X509infost"
    embed="embed"
    ponytypein="X509infost tag"
    ponytypeinconv=""
    ponytypeout="X509infost"
    structtype="X509infost"
    structdef="X509infost"
    argtype="X509infost tag"
    rvtype="X509infost"/>

  <typedef name="Bnmontctxst"
    embed="embed"
    ponytypein="Bnmontctxst tag"
    ponytypeinconv=""
    ponytypeout="Bnmontctxst"
    structtype="Bnmontctxst"
    structdef="Bnmontctxst"
    argtype="Bnmontctxst tag"
    rvtype="Bnmontctxst"/>

  <typedef name="StackstGENERALNAME"
    embed="embed"
    ponytypein="StackstGENERALNAME tag"
    ponytypeinconv=""
    ponytypeout="StackstGENERALNAME"
    structtype="StackstGENERALNAME"
    structdef="StackstGENERALNAME"
    argtype="StackstGENERALNAME tag"
    rvtype="StackstGENERALNAME"/>

  <typedef name="U16"
    embed="var"
    ponytypein="U16"
    ponytypeinconv=""
    ponytypeout="U16"
    structtype="U16"
    structdef="U16(0)"
    argtype="U16"
    rvtype="U16"/>

  <typedef name="POLICYCONSTRAINTSst"
    embed="embed"
    ponytypein="POLICYCONSTRAINTSst tag"
    ponytypeinconv=""
    ponytypeout="POLICYCONSTRAINTSst"
    structtype="POLICYCONSTRAINTSst"
    structdef="POLICYCONSTRAINTSst"
    argtype="POLICYCONSTRAINTSst tag"
    rvtype="POLICYCONSTRAINTSst"/>

  <typedef name="None"
    embed="embed"
    ponytypein="None tag"
    ponytypeinconv=""
    ponytypeout="None"
    structtype="None"
    structdef="None"
    argtype="None tag"
    rvtype="None"/>

  <typedef name="PKCS12MACDATAst"
    embed="embed"
    ponytypein="PKCS12MACDATAst tag"
    ponytypeinconv=""
    ponytypeout="PKCS12MACDATAst"
    structtype="PKCS12MACDATAst"
    structdef="PKCS12MACDATAst"
    argtype="PKCS12MACDATAst tag"
    rvtype="PKCS12MACDATAst"/>

  <typedef name="Enginest"
    embed="embed"
    ponytypein="Enginest tag"
    ponytypeinconv=""
    ponytypeout="Enginest"
    structtype="Enginest"
    structdef="Enginest"
    argtype="Enginest tag"
    rvtype="Enginest"/>

  <typedef name="Anon"
    embed="embed"
    ponytypein="Anon tag"
    ponytypeinconv=""
    ponytypeout="Anon"
    structtype="Anon"
    structdef="Anon"
    argtype="Anon tag"
    rvtype="Anon"/>

  <typedef name="Pkcs12bagst"
    embed="embed"
    ponytypein="Pkcs12bagst tag"
    ponytypeinconv=""
    ponytypeout="Pkcs12bagst"
    structtype="Pkcs12bagst"
    structdef="Pkcs12bagst"
    argtype="Pkcs12bagst tag"
    rvtype="Pkcs12bagst"/>

  <typedef name="ACCESSDESCRIPTIONst"
    embed="embed"
    ponytypein="ACCESSDESCRIPTIONst tag"
    ponytypeinconv=""
    ponytypeout="ACCESSDESCRIPTIONst"
    structtype="ACCESSDESCRIPTIONst"
    structdef="ACCESSDESCRIPTIONst"
    argtype="ACCESSDESCRIPTIONst tag"
    rvtype="ACCESSDESCRIPTIONst"/>

  <typedef name="StackstX509POLICYNODE"
    embed="embed"
    ponytypein="StackstX509POLICYNODE tag"
    ponytypeinconv=""
    ponytypeout="StackstX509POLICYNODE"
    structtype="StackstX509POLICYNODE"
    structdef="StackstX509POLICYNODE"
    argtype="StackstX509POLICYNODE tag"
    rvtype="StackstX509POLICYNODE"/>

  <typedef name="Pointer[U16]"
    embed="var"
    ponytypein="Pointer[U16] tag"
    ponytypeinconv=""
    ponytypeout="Pointer[U16]"
    structtype="Pointer[U16]"
    structdef="Pointer[U16]"
    argtype="Pointer[U16] tag"
    rvtype="Pointer[U16]"/>

  <typedef name="Sslctxst"
    embed="embed"
    ponytypein="Sslctxst tag"
    ponytypeinconv=""
    ponytypeout="Sslctxst"
    structtype="Sslctxst"
    structdef="Sslctxst"
    argtype="Sslctxst tag"
    rvtype="Sslctxst"/>

  <typedef name="SHAstatest"
    embed="embed"
    ponytypein="SHAstatest tag"
    ponytypeinconv=""
    ponytypeout="SHAstatest"
    structtype="SHAstatest"
    structdef="SHAstatest"
    argtype="SHAstatest tag"
    rvtype="SHAstatest"/>

  <typedef name="MD5statest"
    embed="embed"
    ponytypein="MD5statest tag"
    ponytypeinconv=""
    ponytypeout="MD5statest"
    structtype="MD5statest"
    structdef="MD5statest"
    argtype="MD5statest tag"
    rvtype="MD5statest"/>

  <typedef name="LhashstCONFVALUE"
    embed="embed"
    ponytypein="LhashstCONFVALUE tag"
    ponytypeinconv=""
    ponytypeout="LhashstCONFVALUE"
    structtype="LhashstCONFVALUE"
    structdef="LhashstCONFVALUE"
    argtype="LhashstCONFVALUE tag"
    rvtype="LhashstCONFVALUE"/>

  <typedef name="PKEYUSAGEPERIODst"
    embed="embed"
    ponytypein="PKEYUSAGEPERIODst tag"
    ponytypeinconv=""
    ponytypeout="PKEYUSAGEPERIODst"
    structtype="PKEYUSAGEPERIODst"
    structdef="PKEYUSAGEPERIODst"
    argtype="PKEYUSAGEPERIODst tag"
    rvtype="PKEYUSAGEPERIODst"/>

  <typedef name="DISTPOINTst"
    embed="embed"
    ponytypein="DISTPOINTst tag"
    ponytypeinconv=""
    ponytypeout="DISTPOINTst"
    structtype="DISTPOINTst"
    structdef="DISTPOINTst"
    argtype="DISTPOINTst tag"
    rvtype="DISTPOINTst"/>

  <typedef name="Eckeymethodst"
    embed="embed"
    ponytypein="Eckeymethodst tag"
    ponytypeinconv=""
    ponytypeout="Eckeymethodst"
    structtype="Eckeymethodst"
    structdef="Eckeymethodst"
    argtype="Eckeymethodst tag"
    rvtype="Eckeymethodst"/>

  <typedef name="X509crlst"
    embed="embed"
    ponytypein="X509CRL tag"
    ponytypeinconv=""
    ponytypeout="X509CRL"
    structtype="X509CRL"
    structdef="X509CRL"
    argtype="X509CRL tag"
    rvtype="X509CRL"/>

  <typedef name="Pkcs7signerinfost"
    embed="embed"
    ponytypein="Pkcs7signerinfost tag"
    ponytypeinconv=""
    ponytypeout="Pkcs7signerinfost"
    structtype="Pkcs7signerinfost"
    structdef="Pkcs7signerinfost"
    argtype="Pkcs7signerinfost tag"
    rvtype="Pkcs7signerinfost"/>

  <typedef name="Randdrbgst"
    embed="embed"
    ponytypein="Randdrbgst tag"
    ponytypeinconv=""
    ponytypeout="Randdrbgst"
    structtype="Randdrbgst"
    structdef="Randdrbgst"
    argtype="Randdrbgst tag"
    rvtype="Randdrbgst"/>

  <typedef name="Sslsessionst"
    embed="embed"
    ponytypein="Sslsessionst tag"
    ponytypeinconv=""
    ponytypeout="Sslsessionst"
    structtype="Sslsessionst"
    structdef="Sslsessionst"
    argtype="Sslsessionst tag"
    rvtype="Sslsessionst"/>

  <typedef name="Ocsprevokedinfost"
    embed="embed"
    ponytypein="Ocsprevokedinfost tag"
    ponytypeinconv=""
    ponytypeout="Ocsprevokedinfost"
    structtype="Ocsprevokedinfost"
    structdef="Ocsprevokedinfost"
    argtype="Ocsprevokedinfost tag"
    rvtype="Ocsprevokedinfost"/>

  <typedef name="X509algorst"
    embed="embed"
    ponytypein="X509Algor tag"
    ponytypeinconv=""
    ponytypeout="X509Algor"
    structtype="X509Algor"
    structdef="X509Algor"
    argtype="X509Algor tag"
    rvtype="X509Algor"/>

  <typedef name="Evpcipherst"
    embed="embed"
    ponytypein="Evpcipherst tag"
    ponytypeinconv=""
    ponytypeout="Evpcipherst"
    structtype="Evpcipherst"
    structdef="Evpcipherst"
    argtype="Evpcipherst tag"
    rvtype="Evpcipherst"/>

  <typedef name="StackstX509"
    embed="embed"
    ponytypein="StackstX509 tag"
    ponytypeinconv=""
    ponytypeout="StackstX509"
    structtype="StackstX509"
    structdef="StackstX509"
    argtype="StackstX509 tag"
    rvtype="StackstX509"/>

  <typedef name="PROXYCERTINFOEXTENSIONst"
    embed="embed"
    ponytypein="PROXYCERTINFOEXTENSIONst tag"
    ponytypeinconv=""
    ponytypeout="PROXYCERTINFOEXTENSIONst"
    structtype="PROXYCERTINFOEXTENSIONst"
    structdef="PROXYCERTINFOEXTENSIONst"
    argtype="PROXYCERTINFOEXTENSIONst tag"
    rvtype="PROXYCERTINFOEXTENSIONst"/>

  <typedef name="Pkcs8privkeyinfost"
    embed="embed"
    ponytypein="Pkcs8privkeyinfost tag"
    ponytypeinconv=""
    ponytypeout="Pkcs8privkeyinfost"
    structtype="Pkcs8privkeyinfost"
    structdef="Pkcs8privkeyinfost"
    argtype="Pkcs8privkeyinfost tag"
    rvtype="Pkcs8privkeyinfost"/>

  <typedef name="Evpcipherctxst"
    embed="embed"
    ponytypein="Evpcipherctxst tag"
    ponytypeinconv=""
    ponytypeout="Evpcipherctxst"
    structtype="Evpcipherctxst"
    structdef="Evpcipherctxst"
    argtype="Evpcipherctxst tag"
    rvtype="Evpcipherctxst"/>

  <typedef name="StackstASN1OBJECT"
    embed="embed"
    ponytypein="StackstASN1OBJECT tag"
    ponytypeinconv=""
    ponytypeout="StackstASN1OBJECT"
    structtype="StackstASN1OBJECT"
    structdef="StackstASN1OBJECT"
    argtype="StackstASN1OBJECT tag"
    rvtype="StackstASN1OBJECT"/>

  <typedef name="U32"
    embed="var"
    ponytypein="U32"
    ponytypeinconv=""
    ponytypeout="U32"
    structtype="U32"
    structdef="U32(0)"
    argtype="U32"
    rvtype="U32"/>

  <typedef name="Hmacctxst"
    embed="embed"
    ponytypein="Hmacctxst tag"
    ponytypeinconv=""
    ponytypeout="Hmacctxst"
    structtype="Hmacctxst"
    structdef="Hmacctxst"
    argtype="Hmacctxst tag"
    rvtype="Hmacctxst"/>

  <typedef name="StackstADMISSIONS"
    embed="embed"
    ponytypein="StackstADMISSIONS tag"
    ponytypeinconv=""
    ponytypeout="StackstADMISSIONS"
    structtype="StackstADMISSIONS"
    structdef="StackstADMISSIONS"
    argtype="StackstADMISSIONS tag"
    rvtype="StackstADMISSIONS"/>

  <typedef name="CMSCertificateChoices"
    embed="embed"
    ponytypein="CMSCertificateChoices tag"
    ponytypeinconv=""
    ponytypeout="CMSCertificateChoices"
    structtype="CMSCertificateChoices"
    structdef="CMSCertificateChoices"
    argtype="CMSCertificateChoices tag"
    rvtype="CMSCertificateChoices"/>

  <typedef name="DISTPOINTNAMEst"
    embed="embed"
    ponytypein="DISTPOINTNAMEst tag"
    ponytypeinconv=""
    ponytypeout="DISTPOINTNAMEst"
    structtype="DISTPOINTNAMEst"
    structdef="DISTPOINTNAMEst"
    argtype="DISTPOINTNAMEst tag"
    rvtype="DISTPOINTNAMEst"/>

  <typedef name="StackstX509LOOKUP"
    embed="embed"
    ponytypein="StackstX509LOOKUP tag"
    ponytypeinconv=""
    ponytypeout="StackstX509LOOKUP"
    structtype="StackstX509LOOKUP"
    structdef="StackstX509LOOKUP"
    argtype="StackstX509LOOKUP tag"
    rvtype="StackstX509LOOKUP"/>

  <typedef name="X509POLICYNODEst"
    embed="embed"
    ponytypein="X509PolicyNode tag"
    ponytypeinconv=""
    ponytypeout="X509PolicyNode"
    structtype="X509PolicyNode"
    structdef="X509PolicyNode"
    argtype="X509PolicyNode tag"
    rvtype="X509PolicyNode"/>

  <typedef name="Dsamethod"
    embed="embed"
    ponytypein="Dsamethod tag"
    ponytypeinconv=""
    ponytypeout="Dsamethod"
    structtype="Dsamethod"
    structdef="Dsamethod"
    argtype="Dsamethod tag"
    rvtype="Dsamethod"/>

  <typedef name="Ctlogstorest"
    embed="embed"
    ponytypein="Ctlogstorest tag"
    ponytypeinconv=""
    ponytypeout="Ctlogstorest"
    structtype="Ctlogstorest"
    structdef="Ctlogstorest"
    argtype="Ctlogstorest tag"
    rvtype="Ctlogstorest"/>

  <typedef name="..."
    embed="embed"
    ponytypein="... tag"
    ponytypeinconv=""
    ponytypeout="..."
    structtype="..."
    structdef="..."
    argtype="... tag"
    rvtype="..."/>

  <typedef name="GENERALNAMEst"
    embed="embed"
    ponytypein="GENERALNAMEst tag"
    ponytypeinconv=""
    ponytypeout="GENERALNAMEst"
    structtype="GENERALNAMEst"
    structdef="GENERALNAMEst"
    argtype="GENERALNAMEst tag"
    rvtype="GENERALNAMEst"/>

  <typedef name="USERNOTICEst"
    embed="embed"
    ponytypein="USERNOTICEst tag"
    ponytypeinconv=""
    ponytypeout="USERNOTICEst"
    structtype="USERNOTICEst"
    structdef="USERNOTICEst"
    argtype="USERNOTICEst tag"
    rvtype="USERNOTICEst"/>

  <typedef name="StackstCONFIMODULE"
    embed="embed"
    ponytypein="StackstCONFIMODULE tag"
    ponytypeinconv=""
    ponytypeout="StackstCONFIMODULE"
    structtype="StackstCONFIMODULE"
    structdef="StackstCONFIMODULE"
    argtype="StackstCONFIMODULE tag"
    rvtype="StackstCONFIMODULE"/>

  <typedef name="Evppkeymethodst"
    embed="embed"
    ponytypein="Evppkeymethodst tag"
    ponytypeinconv=""
    ponytypeout="Evppkeymethodst"
    structtype="Evppkeymethodst"
    structdef="Evppkeymethodst"
    argtype="Evppkeymethodst tag"
    rvtype="Evppkeymethodst"/>

  <typedef name="Bufmemst"
    embed="embed"
    ponytypein="Bufmemst tag"
    ponytypeinconv=""
    ponytypeout="Bufmemst"
    structtype="Bufmemst"
    structdef="Bufmemst"
    argtype="Bufmemst tag"
    rvtype="Bufmemst"/>

  <typedef name="Pkcs7encryptedst"
    embed="embed"
    ponytypein="Pkcs7encryptedst tag"
    ponytypeinconv=""
    ponytypeout="Pkcs7encryptedst"
    structtype="Pkcs7encryptedst"
    structdef="Pkcs7encryptedst"
    argtype="Pkcs7encryptedst tag"
    rvtype="Pkcs7encryptedst"/>

  <typedef name="X509pubkeyst"
    embed="embed"
    ponytypein="X509pubkeyst tag"
    ponytypeinconv=""
    ponytypeout="X509pubkeyst"
    structtype="X509pubkeyst"
    structdef="X509pubkeyst"
    argtype="X509pubkeyst tag"
    rvtype="X509pubkeyst"/>

  <typedef name="Dsast"
    embed="embed"
    ponytypein="Dsast tag"
    ponytypeinconv=""
    ponytypeout="Dsast"
    structtype="Dsast"
    structdef="Dsast"
    argtype="Dsast tag"
    rvtype="Dsast"/>

  <typedef name="StackstSCT"
    embed="embed"
    ponytypein="StackstSCT tag"
    ponytypeinconv=""
    ponytypeout="StackstSCT"
    structtype="StackstSCT"
    structdef="StackstSCT"
    argtype="StackstSCT tag"
    rvtype="StackstSCT"/>

  <typedef name="SHA256statest"
    embed="embed"
    ponytypein="SHA256statest tag"
    ponytypeinconv=""
    ponytypeout="SHA256statest"
    structtype="SHA256statest"
    structdef="SHA256statest"
    argtype="SHA256statest tag"
    rvtype="SHA256statest"/>

  <typedef name="StackstASN1VALUE"
    embed="embed"
    ponytypein="StackstASN1VALUE tag"
    ponytypeinconv=""
    ponytypeout="StackstASN1VALUE"
    structtype="StackstASN1VALUE"
    structdef="StackstASN1VALUE"
    argtype="StackstASN1VALUE tag"
    rvtype="StackstASN1VALUE"/>

  <typedef name="X509nameentryst"
    embed="embed"
    ponytypein="X509nameentryst tag"
    ponytypeinconv=""
    ponytypeout="X509nameentryst"
    structtype="X509nameentryst"
    structdef="X509nameentryst"
    argtype="X509nameentryst tag"
    rvtype="X509nameentryst"/>

  <typedef name="BIGNum"
    embed="embed"
    ponytypein="BIGNum tag"
    ponytypeinconv=""
    ponytypeout="BIGNum"
    structtype="BIGNum"
    structdef="BIGNum"
    argtype="BIGNum tag"
    rvtype="BIGNum"/>

  <typedef name="StackstASN1TYPE"
    embed="embed"
    ponytypein="StackstASN1TYPE tag"
    ponytypeinconv=""
    ponytypeout="StackstASN1TYPE"
    structtype="StackstASN1TYPE"
    structdef="StackstASN1TYPE"
    argtype="StackstASN1TYPE tag"
    rvtype="StackstASN1TYPE"/>

  <typedef name="Pointer[U8]"
    embed="var"
    ponytypein="Pointer[U8] tag"
    ponytypeinconv=""
    ponytypeout="Pointer[U8]"
    structtype="Pointer[U8]"
    structdef="Pointer[U8]"
    argtype="Pointer[U8] tag"
    rvtype="Pointer[U8]"/>

  <typedef name="ASN1TLCst"
    embed="embed"
    ponytypein="ASN1TLCst tag"
    ponytypeinconv=""
    ponytypeout="ASN1TLCst"
    structtype="ASN1TLCst"
    structdef="ASN1TLCst"
    argtype="ASN1TLCst tag"
    rvtype="ASN1TLCst"/>

  <typedef name="StackstX509PURPOSE"
    embed="embed"
    ponytypein="StackstX509PURPOSE tag"
    ponytypeinconv=""
    ponytypeout="StackstX509PURPOSE"
    structtype="StackstX509PURPOSE"
    structdef="StackstX509PURPOSE"
    argtype="StackstX509PURPOSE tag"
    rvtype="StackstX509PURPOSE"/>

  <typedef name="SXNETIDst"
    embed="embed"
    ponytypein="SXNETIDst tag"
    ponytypeinconv=""
    ponytypeout="SXNETIDst"
    structtype="SXNETIDst"
    structdef="SXNETIDst"
    argtype="SXNETIDst tag"
    rvtype="SXNETIDst"/>

  <typedef name="X509trustst"
    embed="embed"
    ponytypein="X509trustst tag"
    ponytypeinconv=""
    ponytypeout="X509trustst"
    structtype="X509trustst"
    structdef="X509trustst"
    argtype="X509trustst tag"
    rvtype="X509trustst"/>

  <typedef name="SCRYPTPARAMSst"
    embed="embed"
    ponytypein="SCRYPTPARAMSst tag"
    ponytypeinconv=""
    ponytypeout="SCRYPTPARAMSst"
    structtype="SCRYPTPARAMSst"
    structdef="SCRYPTPARAMSst"
    argtype="SCRYPTPARAMSst tag"
    rvtype="SCRYPTPARAMSst"/>

  <typedef name="X509attributesst"
    embed="embed"
    ponytypein="X509attributesst tag"
    ponytypeinconv=""
    ponytypeout="X509attributesst"
    structtype="X509attributesst"
    structdef="X509attributesst"
    argtype="X509attributesst tag"
    rvtype="X509attributesst"/>

  <typedef name="Confmethodst"
    embed="embed"
    ponytypein="Confmethodst tag"
    ponytypeinconv=""
    ponytypeout="Confmethodst"
    structtype="Confmethodst"
    structdef="Confmethodst"
    argtype="Confmethodst tag"
    rvtype="Confmethodst"/>

  <typedef name="Pointer[I64]"
    embed="var"
    ponytypein="Pointer[I64] tag"
    ponytypeinconv=""
    ponytypeout="Pointer[I64]"
    structtype="Pointer[I64]"
    structdef="Pointer[I64]"
    argtype="Pointer[I64] tag"
    rvtype="Pointer[I64]"/>

  <typedef name="Sslmethodst"
    embed="embed"
    ponytypein="Sslmethodst tag"
    ponytypeinconv=""
    ponytypeout="Sslmethodst"
    structtype="Sslmethodst"
    structdef="Sslmethodst"
    argtype="Sslmethodst tag"
    rvtype="Sslmethodst"/>

  <typedef name="V3extctx"
    embed="embed"
    ponytypein="V3extctx tag"
    ponytypeinconv=""
    ponytypeout="V3extctx"
    structtype="V3extctx"
    structdef="V3extctx"
    argtype="V3extctx tag"
    rvtype="V3extctx"/>

  <typedef name="ASN1TEMPLATEst"
    embed="embed"
    ponytypein="ASN1TEMPLATEst tag"
    ponytypeinconv=""
    ponytypeout="ASN1TEMPLATEst"
    structtype="ASN1TEMPLATEst"
    structdef="ASN1TEMPLATEst"
    argtype="ASN1TEMPLATEst tag"
    rvtype="ASN1TEMPLATEst"/>

  <typedef name="Stackstvoid"
    embed="embed"
    ponytypein="Stackstvoid tag"
    ponytypeinconv=""
    ponytypeout="Stackstvoid"
    structtype="Stackstvoid"
    structdef="Stackstvoid"
    argtype="Stackstvoid tag"
    rvtype="Stackstvoid"/>

  <typedef name="X509sigst"
    embed="embed"
    ponytypein="X509sigst tag"
    ponytypeinconv=""
    ponytypeout="X509sigst"
    structtype="X509sigst"
    structdef="X509sigst"
    argtype="X509sigst tag"
    rvtype="X509sigst"/>

  <typedef name="Asn1objectst"
    embed="embed"
    ponytypein="Asn1objectst tag"
    ponytypeinconv=""
    ponytypeout="Asn1objectst"
    structtype="Asn1objectst"
    structdef="Asn1objectst"
    argtype="Asn1objectst tag"
    rvtype="Asn1objectst"/>

  <typedef name="Netscapespkacst"
    embed="embed"
    ponytypein="Netscapespkacst tag"
    ponytypeinconv=""
    ponytypeout="Netscapespkacst"
    structtype="Netscapespkacst"
    structdef="Netscapespkacst"
    argtype="Netscapespkacst tag"
    rvtype="Netscapespkacst"/>

  <typedef name="Cryptoexdatast"
    embed="embed"
    ponytypein="Cryptoexdatast tag"
    ponytypeinconv=""
    ponytypeout="Cryptoexdatast"
    structtype="Cryptoexdatast"
    structdef="Cryptoexdatast"
    argtype="Cryptoexdatast tag"
    rvtype="Cryptoexdatast"/>

  <typedef name="Pointer[I32]"
    embed="var"
    ponytypein="Pointer[I32] tag"
    ponytypeinconv=""
    ponytypeout="Pointer[I32]"
    structtype="Pointer[I32]"
    structdef="Pointer[I32]"
    argtype="Pointer[I32] tag"
    rvtype="Pointer[I32]"/>

  <typedef name="StackstPOLICYQUALINFO"
    embed="embed"
    ponytypein="StackstPOLICYQUALINFO tag"
    ponytypeinconv=""
    ponytypeout="StackstPOLICYQUALINFO"
    structtype="StackstPOLICYQUALINFO"
    structdef="StackstPOLICYQUALINFO"
    argtype="StackstPOLICYQUALINFO tag"
    rvtype="StackstPOLICYQUALINFO"/>

  <typedef name="StackstCMSRecipientEncryptedKey"
    embed="embed"
    ponytypein="StackstCMSRecipientEncryptedKey tag"
    ponytypeinconv=""
    ponytypeout="StackstCMSRecipientEncryptedKey"
    structtype="StackstCMSRecipientEncryptedKey"
    structdef="StackstCMSRecipientEncryptedKey"
    argtype="StackstCMSRecipientEncryptedKey tag"
    rvtype="StackstCMSRecipientEncryptedKey"/>

  <typedef name="GENERALSUBTREEst"
    embed="embed"
    ponytypein="GENERALSUBTREEst tag"
    ponytypeinconv=""
    ponytypeout="GENERALSUBTREEst"
    structtype="GENERALSUBTREEst"
    structdef="GENERALSUBTREEst"
    argtype="GENERALSUBTREEst tag"
    rvtype="GENERALSUBTREEst"/>

  <typedef name="StackstCMSSignerInfo"
    embed="embed"
    ponytypein="StackstCMSSignerInfo tag"
    ponytypeinconv=""
    ponytypeout="StackstCMSSignerInfo"
    structtype="StackstCMSSignerInfo"
    structdef="StackstCMSSignerInfo"
    argtype="StackstCMSSignerInfo tag"
    rvtype="StackstCMSSignerInfo"/>

  <typedef name="Compctxst"
    embed="embed"
    ponytypein="Compctxst tag"
    ponytypeinconv=""
    ponytypeout="Compctxst"
    structtype="Compctxst"
    structdef="Compctxst"
    argtype="Compctxst tag"
    rvtype="Compctxst"/>

  <typedef name="AUTHORITYKEYIDst"
    embed="embed"
    ponytypein="AUTHORITYKEYIDst tag"
    ponytypeinconv=""
    ponytypeout="AUTHORITYKEYIDst"
    structtype="AUTHORITYKEYIDst"
    structdef="AUTHORITYKEYIDst"
    argtype="AUTHORITYKEYIDst tag"
    rvtype="AUTHORITYKEYIDst"/>

  <typedef name="Bignumctx"
    embed="embed"
    ponytypein="Bignumctx tag"
    ponytypeinconv=""
    ponytypeout="Bignumctx"
    structtype="Bignumctx"
    structdef="Bignumctx"
    argtype="Bignumctx tag"
    rvtype="Bignumctx"/>

  <typedef name="IPAddressOrRangest"
    embed="embed"
    ponytypein="IPAddressOrRangest tag"
    ponytypeinconv=""
    ponytypeout="IPAddressOrRangest"
    structtype="IPAddressOrRangest"
    structdef="IPAddressOrRangest"
    argtype="IPAddressOrRangest tag"
    rvtype="IPAddressOrRangest"/>

  <typedef name="CMSContentInfost"
    embed="embed"
    ponytypein="CMSContentInfost tag"
    ponytypeinconv=""
    ponytypeout="CMSContentInfost"
    structtype="CMSContentInfost"
    structdef="CMSContentInfost"
    argtype="CMSContentInfost tag"
    rvtype="CMSContentInfost"/>

  <typedef name="StackstCTLOG"
    embed="embed"
    ponytypein="StackstCTLOG tag"
    ponytypeinconv=""
    ponytypeout="StackstCTLOG"
    structtype="StackstCTLOG"
    structdef="StackstCTLOG"
    argtype="StackstCTLOG tag"
    rvtype="StackstCTLOG"/>

  <typedef name="StackstASN1INTEGER"
    embed="embed"
    ponytypein="StackstASN1INTEGER tag"
    ponytypeinconv=""
    ponytypeout="StackstASN1INTEGER"
    structtype="StackstASN1INTEGER"
    structdef="StackstASN1INTEGER"
    argtype="StackstASN1INTEGER tag"
    rvtype="StackstASN1INTEGER"/>

  <typedef name="StackstOPENSSLCSTRING"
    embed="embed"
    ponytypein="StackstOPENSSLCSTRING tag"
    ponytypeinconv=""
    ponytypeout="StackstOPENSSLCSTRING"
    structtype="StackstOPENSSLCSTRING"
    structdef="StackstOPENSSLCSTRING"
    argtype="StackstOPENSSLCSTRING tag"
    rvtype="StackstOPENSSLCSTRING"/>

  <typedef name="Asn1sctxst"
    embed="embed"
    ponytypein="Asn1sctxst tag"
    ponytypeinconv=""
    ponytypeout="Asn1sctxst"
    structtype="Asn1sctxst"
    structdef="Asn1sctxst"
    argtype="Asn1sctxst tag"
    rvtype="Asn1sctxst"/>

  <typedef name="X509reqinfost"
    embed="embed"
    ponytypein="X509reqinfost tag"
    ponytypeinconv=""
    ponytypeout="X509reqinfost"
    structtype="X509reqinfost"
    structdef="X509reqinfost"
    argtype="X509reqinfost tag"
    rvtype="X509reqinfost"/>

  <typedef name="ASIdentifierChoicest"
    embed="embed"
    ponytypein="ASIdentifierChoicest tag"
    ponytypeinconv=""
    ponytypeout="ASIdentifierChoicest"
    structtype="ASIdentifierChoicest"
    structdef="ASIdentifierChoicest"
    argtype="ASIdentifierChoicest tag"
    rvtype="ASIdentifierChoicest"/>

  <typedef name="Mdc2ctxst"
    embed="embed"
    ponytypein="Mdc2ctxst tag"
    ponytypeinconv=""
    ponytypeout="Mdc2ctxst"
    structtype="Mdc2ctxst"
    structdef="Mdc2ctxst"
    argtype="Mdc2ctxst tag"
    rvtype="Mdc2ctxst"/>

  <typedef name="Evppkeyasn1methodst"
    embed="embed"
    ponytypein="Evppkeyasn1methodst tag"
    ponytypeinconv=""
    ponytypeout="Evppkeyasn1methodst"
    structtype="Evppkeyasn1methodst"
    structdef="Evppkeyasn1methodst"
    argtype="Evppkeyasn1methodst tag"
    rvtype="Evppkeyasn1methodst"/>

  <typedef name="POLICYMAPPINGst"
    embed="embed"
    ponytypein="POLICYMAPPINGst tag"
    ponytypeinconv=""
    ponytypeout="POLICYMAPPINGst"
    structtype="POLICYMAPPINGst"
    structdef="POLICYMAPPINGst"
    argtype="POLICYMAPPINGst tag"
    rvtype="POLICYMAPPINGst"/>

  <typedef name="PROXYPOLICYst"
    embed="embed"
    ponytypein="PROXYPOLICYst tag"
    ponytypeinconv=""
    ponytypeout="PROXYPOLICYst"
    structtype="PROXYPOLICYst"
    structdef="PROXYPOLICYst"
    argtype="PROXYPOLICYst tag"
    rvtype="PROXYPOLICYst"/>

  <typedef name="Netscapespkist"
    embed="embed"
    ponytypein="Netscapespkist tag"
    ponytypeinconv=""
    ponytypeout="Netscapespkist"
    structtype="Netscapespkist"
    structdef="Netscapespkist"
    argtype="Netscapespkist tag"
    rvtype="Netscapespkist"/>

  <typedef name="Eckeyst"
    embed="embed"
    ponytypein="Eckeyst tag"
    ponytypeinconv=""
    ponytypeout="Eckeyst"
    structtype="Eckeyst"
    structdef="Eckeyst"
    argtype="Eckeyst tag"
    rvtype="Eckeyst"/>

  <typedef name="IPAddressChoicest"
    embed="embed"
    ponytypein="IPAddressChoicest tag"
    ponytypeinconv=""
    ponytypeout="IPAddressChoicest"
    structtype="IPAddressChoicest"
    structdef="IPAddressChoicest"
    argtype="IPAddressChoicest tag"
    rvtype="IPAddressChoicest"/>

  <typedef name="Rsaoaepparamsst"
    embed="embed"
    ponytypein="Rsaoaepparamsst tag"
    ponytypeinconv=""
    ponytypeout="Rsaoaepparamsst"
    structtype="Rsaoaepparamsst"
    structdef="Rsaoaepparamsst"
    argtype="Rsaoaepparamsst tag"
    rvtype="Rsaoaepparamsst"/>

  <typedef name="Sslcipherst"
    embed="embed"
    ponytypein="Sslcipherst tag"
    ponytypeinconv=""
    ponytypeout="Sslcipherst"
    structtype="Sslcipherst"
    structdef="Sslcipherst"
    argtype="Sslcipherst tag"
    rvtype="Sslcipherst"/>

  <typedef name="StackstCONFMODULE"
    embed="embed"
    ponytypein="StackstCONFMODULE tag"
    ponytypeinconv=""
    ponytypeout="StackstCONFMODULE"
    structtype="StackstCONFMODULE"
    structdef="StackstCONFMODULE"
    argtype="StackstCONFMODULE tag"
    rvtype="StackstCONFMODULE"/>

  <typedef name="StackstOCSPCERTID"
    embed="embed"
    ponytypein="StackstOCSPCERTID tag"
    ponytypeinconv=""
    ponytypeout="StackstOCSPCERTID"
    structtype="StackstOCSPCERTID"
    structdef="StackstOCSPCERTID"
    argtype="StackstOCSPCERTID tag"
    rvtype="StackstOCSPCERTID"/>

  <typedef name="SXNETst"
    embed="embed"
    ponytypein="SXNETst tag"
    ponytypeinconv=""
    ponytypeout="SXNETst"
    structtype="SXNETst"
    structdef="SXNETst"
    argtype="SXNETst tag"
    rvtype="SXNETst"/>

  <typedef name="Pkcs7st"
    embed="embed"
    ponytypein="Pkcs7st tag"
    ponytypeinconv=""
    ponytypeout="Pkcs7st"
    structtype="Pkcs7st"
    structdef="Pkcs7st"
    argtype="Pkcs7st tag"
    rvtype="Pkcs7st"/>

  <typedef name="Errstatest"
    embed="embed"
    ponytypein="Errstatest tag"
    ponytypeinconv=""
    ponytypeout="Errstatest"
    structtype="Errstatest"
    structdef="Errstatest"
    argtype="Errstatest tag"
    rvtype="Errstatest"/>

  <typedef name="Ocspbasicresponsest"
    embed="embed"
    ponytypein="Ocspbasicresponsest tag"
    ponytypeinconv=""
    ponytypeout="Ocspbasicresponsest"
    structtype="Ocspbasicresponsest"
    structdef="Ocspbasicresponsest"
    argtype="Ocspbasicresponsest tag"
    rvtype="Ocspbasicresponsest"/>

  <typedef name="Asyncjobst"
    embed="embed"
    ponytypein="Asyncjobst tag"
    ponytypeinconv=""
    ponytypeout="Asyncjobst"
    structtype="Asyncjobst"
    structdef="Asyncjobst"
    argtype="Asyncjobst tag"
    rvtype="Asyncjobst"/>

  <typedef name="Ocspresponderidst"
    embed="embed"
    ponytypein="Ocspresponderidst tag"
    ponytypeinconv=""
    ponytypeout="Ocspresponderidst"
    structtype="Ocspresponderidst"
    structdef="Ocspresponderidst"
    argtype="Ocspresponderidst tag"
    rvtype="Ocspresponderidst"/>

  <typedef name="ProfessionInfost"
    embed="embed"
    ponytypein="ProfessionInfost tag"
    ponytypeinconv=""
    ponytypeout="ProfessionInfost"
    structtype="ProfessionInfost"
    structdef="ProfessionInfost"
    argtype="ProfessionInfost tag"
    rvtype="ProfessionInfost"/>

  <typedef name="Ecpointst"
    embed="embed"
    ponytypein="Ecpointst tag"
    ponytypeinconv=""
    ponytypeout="Ecpointst"
    structtype="Ecpointst"
    structdef="Ecpointst"
    argtype="Ecpointst tag"
    rvtype="Ecpointst"/>

  <typedef name="Ocspsignaturest"
    embed="embed"
    ponytypein="Ocspsignaturest tag"
    ponytypeinconv=""
    ponytypeout="Ocspsignaturest"
    structtype="Ocspsignaturest"
    structdef="Ocspsignaturest"
    argtype="Ocspsignaturest tag"
    rvtype="Ocspsignaturest"/>

  <typedef name="Ocspservicelocatorst"
    embed="embed"
    ponytypein="Ocspservicelocatorst tag"
    ponytypeinconv=""
    ponytypeout="Ocspservicelocatorst"
    structtype="Ocspservicelocatorst"
    structdef="Ocspservicelocatorst"
    argtype="Ocspservicelocatorst tag"
    rvtype="Ocspservicelocatorst"/>

  <typedef name="Confmodulest"
    embed="embed"
    ponytypein="Confmodulest tag"
    ponytypeinconv=""
    ponytypeout="Confmodulest"
    structtype="Confmodulest"
    structdef="Confmodulest"
    argtype="Confmodulest tag"
    rvtype="Confmodulest"/>

  <typedef name="StackstDISTPOINT"
    embed="embed"
    ponytypein="StackstDISTPOINT tag"
    ponytypeinconv=""
    ponytypeout="StackstDISTPOINT"
    structtype="StackstDISTPOINT"
    structdef="StackstDISTPOINT"
    argtype="StackstDISTPOINT tag"
    rvtype="StackstDISTPOINT"/>

  <typedef name="Pointer[U64]"
    embed="var"
    ponytypein="Pointer[U64] tag"
    ponytypeinconv=""
    ponytypeout="Pointer[U64]"
    structtype="Pointer[U64]"
    structdef="Pointer[U64]"
    argtype="Pointer[U64] tag"
    rvtype="Pointer[U64]"/>

  <typedef name="V3extmethod"
    embed="embed"
    ponytypein="V3extmethod tag"
    ponytypeinconv=""
    ponytypeout="V3extmethod"
    structtype="V3extmethod"
    structdef="V3extmethod"
    argtype="V3extmethod tag"
    rvtype="V3extmethod"/>

  <typedef name="StackstBIO"
    embed="embed"
    ponytypein="StackstBIO tag"
    ponytypeinconv=""
    ponytypeout="StackstBIO"
    structtype="StackstBIO"
    structdef="StackstBIO"
    argtype="StackstBIO tag"
    rvtype="StackstBIO"/>

  <typedef name="StackstOCSPRESPID"
    embed="embed"
    ponytypein="StackstOCSPRESPID tag"
    ponytypeinconv=""
    ponytypeout="StackstOCSPRESPID"
    structtype="StackstOCSPRESPID"
    structdef="StackstOCSPRESPID"
    argtype="StackstOCSPRESPID tag"
    rvtype="StackstOCSPRESPID"/>

  <typedef name="DSASIGst"
    embed="embed"
    ponytypein="DSASIGst tag"
    ponytypeinconv=""
    ponytypeout="DSASIGst"
    structtype="DSASIGst"
    structdef="DSASIGst"
    argtype="DSASIGst tag"
    rvtype="DSASIGst"/>

  <typedef name="StackstPKCS7RECIPINFO"
    embed="embed"
    ponytypein="StackstPKCS7RECIPINFO tag"
    ponytypeinconv=""
    ponytypeout="StackstPKCS7RECIPINFO"
    structtype="StackstPKCS7RECIPINFO"
    structdef="StackstPKCS7RECIPINFO"
    argtype="StackstPKCS7RECIPINFO tag"
    rvtype="StackstPKCS7RECIPINFO"/>

  <typedef name="StackstGENERALSUBTREE"
    embed="embed"
    ponytypein="StackstGENERALSUBTREE tag"
    ponytypeinconv=""
    ponytypeout="StackstGENERALSUBTREE"
    structtype="StackstGENERALSUBTREE"
    structdef="StackstGENERALSUBTREE"
    argtype="StackstGENERALSUBTREE tag"
    rvtype="StackstGENERALSUBTREE"/>

  <typedef name="Pkcs7digestst"
    embed="embed"
    ponytypein="Pkcs7digestst tag"
    ponytypeinconv=""
    ponytypeout="Pkcs7digestst"
    structtype="Pkcs7digestst"
    structdef="Pkcs7digestst"
    argtype="Pkcs7digestst tag"
    rvtype="Pkcs7digestst"/>

  <typedef name="Ecmethodst"
    embed="embed"
    ponytypein="Ecmethodst tag"
    ponytypeinconv=""
    ponytypeout="Ecmethodst"
    structtype="Ecmethodst"
    structdef="Ecmethodst"
    argtype="Ecmethodst tag"
    rvtype="Ecmethodst"/>

  <typedef name="Confimodulest"
    embed="embed"
    ponytypein="Confimodulest tag"
    ponytypeinconv=""
    ponytypeout="Confimodulest"
    structtype="Confimodulest"
    structdef="Confimodulest"
    argtype="Confimodulest tag"
    rvtype="Confimodulest"/>

  <typedef name="ISSUINGDISTPOINTst"
    embed="embed"
    ponytypein="ISSUINGDISTPOINTst tag"
    ponytypeinconv=""
    ponytypeout="ISSUINGDISTPOINTst"
    structtype="ISSUINGDISTPOINTst"
    structdef="ISSUINGDISTPOINTst"
    argtype="ISSUINGDISTPOINTst tag"
    rvtype="ISSUINGDISTPOINTst"/>

  <typedef name="StackstASN1UTF8STRING"
    embed="embed"
    ponytypein="StackstASN1UTF8STRING tag"
    ponytypeinconv=""
    ponytypeout="StackstASN1UTF8STRING"
    structtype="StackstASN1UTF8STRING"
    structdef="StackstASN1UTF8STRING"
    argtype="StackstASN1UTF8STRING tag"
    rvtype="StackstASN1UTF8STRING"/>

  <typedef name="BIO"
    embed="embed"
    ponytypein="BIO tag"
    ponytypeinconv=""
    ponytypeout="BIO"
    structtype="BIO"
    structdef="BIO"
    argtype="BIO tag"
    rvtype="BIO"/>

  <typedef name="EDIPartyNamest"
    embed="embed"
    ponytypein="EDIPartyNamest tag"
    ponytypeinconv=""
    ponytypeout="EDIPartyNamest"
    structtype="EDIPartyNamest"
    structdef="EDIPartyNamest"
    argtype="EDIPartyNamest tag"
    rvtype="EDIPartyNamest"/>

  <typedef name="X509POLICYTREEst"
    embed="embed"
    ponytypein="X509POLICYTREEst tag"
    ponytypeinconv=""
    ponytypeout="X509POLICYTREEst"
    structtype="X509POLICYTREEst"
    structdef="X509POLICYTREEst"
    argtype="X509POLICYTREEst tag"
    rvtype="X509POLICYTREEst"/>

  <typedef name="Pointer[None]"
    embed="var"
    ponytypein="Pointer[None] tag"
    ponytypeinconv=""
    ponytypeout="Pointer[None]"
    structtype="Pointer[None]"
    structdef="Pointer[None]"
    argtype="Pointer[None] tag"
    rvtype="Pointer[None]"/>

  <typedef name="StackstX509VERIFYPARAM"
    embed="embed"
    ponytypein="StackstX509VERIFYPARAM tag"
    ponytypeinconv=""
    ponytypeout="StackstX509VERIFYPARAM"
    structtype="StackstX509VERIFYPARAM"
    structdef="StackstX509VERIFYPARAM"
    argtype="StackstX509VERIFYPARAM tag"
    rvtype="StackstX509VERIFYPARAM"/>

  <typedef name="StackstPKCS7"
    embed="embed"
    ponytypein="StackstPKCS7 tag"
    ponytypeinconv=""
    ponytypeout="StackstPKCS7"
    structtype="StackstPKCS7"
    structdef="StackstPKCS7"
    argtype="StackstPKCS7 tag"
    rvtype="StackstPKCS7"/>

  <typedef name="StackstSRTPPROTECTIONPROFILE"
    embed="embed"
    ponytypein="StackstSRTPPROTECTIONPROFILE tag"
    ponytypeinconv=""
    ponytypeout="StackstSRTPPROTECTIONPROFILE"
    structtype="StackstSRTPPROTECTIONPROFILE"
    structdef="StackstSRTPPROTECTIONPROFILE"
    argtype="StackstSRTPPROTECTIONPROFILE tag"
    rvtype="StackstSRTPPROTECTIONPROFILE"/>

  <typedef name="StackstACCESSDESCRIPTION"
    embed="embed"
    ponytypein="StackstACCESSDESCRIPTION tag"
    ponytypeinconv=""
    ponytypeout="StackstACCESSDESCRIPTION"
    structtype="StackstACCESSDESCRIPTION"
    structdef="StackstACCESSDESCRIPTION"
    argtype="StackstACCESSDESCRIPTION tag"
    rvtype="StackstACCESSDESCRIPTION"/>

  <typedef name="StackstASIdOrRange"
    embed="embed"
    ponytypein="StackstASIdOrRange tag"
    ponytypeinconv=""
    ponytypeout="StackstASIdOrRange"
    structtype="StackstASIdOrRange"
    structdef="StackstASIdOrRange"
    argtype="StackstASIdOrRange tag"
    rvtype="StackstASIdOrRange"/>

  <typedef name="EvpEncodeCtxst"
    embed="embed"
    ponytypein="EvpEncodeCtxst tag"
    ponytypeinconv=""
    ponytypeout="EvpEncodeCtxst"
    structtype="EvpEncodeCtxst"
    structdef="EvpEncodeCtxst"
    argtype="EvpEncodeCtxst tag"
    rvtype="EvpEncodeCtxst"/>

  <typedef name="Pkcs7envelopedst"
    embed="embed"
    ponytypein="Pkcs7envelopedst tag"
    ponytypeinconv=""
    ponytypeout="Pkcs7envelopedst"
    structtype="Pkcs7envelopedst"
    structdef="Pkcs7envelopedst"
    argtype="Pkcs7envelopedst tag"
    rvtype="Pkcs7envelopedst"/>

  <typedef name="Sslcompst"
    embed="embed"
    ponytypein="Sslcompst tag"
    ponytypeinconv=""
    ponytypeout="Sslcompst"
    structtype="Sslcompst"
    structdef="Sslcompst"
    argtype="Sslcompst tag"
    rvtype="Sslcompst"/>

  <typedef name="LhashstERRSTRINGDATA"
    embed="embed"
    ponytypein="LhashstERRSTRINGDATA tag"
    ponytypeinconv=""
    ponytypeout="LhashstERRSTRINGDATA"
    structtype="LhashstERRSTRINGDATA"
    structdef="LhashstERRSTRINGDATA"
    argtype="LhashstERRSTRINGDATA tag"
    rvtype="LhashstERRSTRINGDATA"/>

  <typedef name="Bnblindingst"
    embed="embed"
    ponytypein="Bnblindingst tag"
    ponytypeinconv=""
    ponytypeout="Bnblindingst"
    structtype="Bnblindingst"
    structdef="Bnblindingst"
    argtype="Bnblindingst tag"
    rvtype="Bnblindingst"/>

  <typedef name="Ocsprequestst"
    embed="embed"
    ponytypein="Ocsprequestst tag"
    ponytypeinconv=""
    ponytypeout="Ocsprequestst"
    structtype="Ocsprequestst"
    structdef="Ocsprequestst"
    argtype="Ocsprequestst tag"
    rvtype="Ocsprequestst"/>

  <typedef name="Biomethodst"
    embed="embed"
    ponytypein="BIOMethod tag"
    ponytypeinconv=""
    ponytypeout="BIOMethod"
    structtype="BIOMethod"
    structdef="BIOMethod"
    argtype="BIOMethod tag"
    rvtype="BIOMethod"/>

  <typedef name="LhashstSSLSESSION"
    embed="embed"
    ponytypein="LhashstSSLSESSION tag"
    ponytypeinconv=""
    ponytypeout="LhashstSSLSESSION"
    structtype="LhashstSSLSESSION"
    structdef="LhashstSSLSESSION"
    argtype="LhashstSSLSESSION tag"
    rvtype="LhashstSSLSESSION"/>

  <typedef name="Osslstoresearchst"
    embed="embed"
    ponytypein="Osslstoresearchst tag"
    ponytypeinconv=""
    ponytypeout="Osslstoresearchst"
    structtype="Osslstoresearchst"
    structdef="Osslstoresearchst"
    argtype="Osslstoresearchst tag"
    rvtype="Osslstoresearchst"/>

  <typedef name="StackstX509TRUST"
    embed="embed"
    ponytypein="StackstX509TRUST tag"
    ponytypeinconv=""
    ponytypeout="StackstX509TRUST"
    structtype="StackstX509TRUST"
    structdef="StackstX509TRUST"
    argtype="StackstX509TRUST tag"
    rvtype="StackstX509TRUST"/>

  <typedef name="Privatekeyst"
    embed="embed"
    ponytypein="Privatekeyst tag"
    ponytypeinconv=""
    ponytypeout="Privatekeyst"
    structtype="Privatekeyst"
    structdef="Privatekeyst"
    argtype="Privatekeyst tag"
    rvtype="Privatekeyst"/>

  <typedef name="Netscapecertificatesequence"
    embed="embed"
    ponytypein="Netscapecertificatesequence tag"
    ponytypeinconv=""
    ponytypeout="Netscapecertificatesequence"
    structtype="Netscapecertificatesequence"
    structdef="Netscapecertificatesequence"
    argtype="Netscapecertificatesequence tag"
    rvtype="Netscapecertificatesequence"/>

  <typedef name="BITSTRINGBITNAMEst"
    embed="embed"
    ponytypein="BITSTRINGBITNAMEst tag"
    ponytypeinconv=""
    ponytypeout="BITSTRINGBITNAMEst"
    structtype="BITSTRINGBITNAMEst"
    structdef="BITSTRINGBITNAMEst"
    argtype="BITSTRINGBITNAMEst tag"
    rvtype="BITSTRINGBITNAMEst"/>

  <typedef name="Osslstoreinfost"
    embed="embed"
    ponytypein="Osslstoreinfost tag"
    ponytypeinconv=""
    ponytypeout="Osslstoreinfost"
    structtype="Osslstoreinfost"
    structdef="Osslstoreinfost"
    argtype="Osslstoreinfost tag"
    rvtype="Osslstoreinfost"/>

  <typedef name="LhashstOPENSSLCSTRING"
    embed="embed"
    ponytypein="LhashstOPENSSLCSTRING tag"
    ponytypeinconv=""
    ponytypeout="LhashstOPENSSLCSTRING"
    structtype="LhashstOPENSSLCSTRING"
    structdef="LhashstOPENSSLCSTRING"
    argtype="LhashstOPENSSLCSTRING tag"
    rvtype="LhashstOPENSSLCSTRING"/>

  <typedef name="CMSRecipientEncryptedKeyst"
    embed="embed"
    ponytypein="CMSRecipientEncryptedKeyst tag"
    ponytypeinconv=""
    ponytypeout="CMSRecipientEncryptedKeyst"
    structtype="CMSRecipientEncryptedKeyst"
    structdef="CMSRecipientEncryptedKeyst"
    argtype="CMSRecipientEncryptedKeyst tag"
    rvtype="CMSRecipientEncryptedKeyst"/>

  <typedef name="BASICCONSTRAINTSst"
    embed="embed"
    ponytypein="BASICCONSTRAINTSst tag"
    ponytypeinconv=""
    ponytypeout="BASICCONSTRAINTSst"
    structtype="BASICCONSTRAINTSst"
    structdef="BASICCONSTRAINTSst"
    argtype="BASICCONSTRAINTSst tag"
    rvtype="BASICCONSTRAINTSst"/>

  <typedef name="Ctlogst"
    embed="embed"
    ponytypein="Ctlogst tag"
    ponytypeinconv=""
    ponytypeout="Ctlogst"
    structtype="Ctlogst"
    structdef="Ctlogst"
    argtype="Ctlogst tag"
    rvtype="Ctlogst"/>

  <typedef name="ASIdOrRangest"
    embed="embed"
    ponytypein="ASIdOrRangest tag"
    ponytypeinconv=""
    ponytypeout="ASIdOrRangest"
    structtype="ASIdOrRangest"
    structdef="ASIdOrRangest"
    argtype="ASIdOrRangest tag"
    rvtype="ASIdOrRangest"/>

  <typedef name="ECDSASIGst"
    embed="embed"
    ponytypein="ECDSASIGst tag"
    ponytypeinconv=""
    ponytypeout="ECDSASIGst"
    structtype="ECDSASIGst"
    structdef="ECDSASIGst"
    argtype="ECDSASIGst tag"
    rvtype="ECDSASIGst"/>

  <typedef name="Ocspreqctxst"
    embed="embed"
    ponytypein="Ocspreqctxst tag"
    ponytypeinconv=""
    ponytypeout="Ocspreqctxst"
    structtype="Ocspreqctxst"
    structdef="Ocspreqctxst"
    argtype="Ocspreqctxst tag"
    rvtype="Ocspreqctxst"/>

  <typedef name="X509lookupmethodst"
    embed="embed"
    ponytypein="X509lookupmethodst tag"
    ponytypeinconv=""
    ponytypeout="X509lookupmethodst"
    structtype="X509lookupmethodst"
    structdef="X509lookupmethodst"
    argtype="X509lookupmethodst tag"
    rvtype="X509lookupmethodst"/>

  <typedef name="StackstX509NAME"
    embed="embed"
    ponytypein="StackstX509NAME tag"
    ponytypeinconv=""
    ponytypeout="StackstX509NAME"
    structtype="StackstX509NAME"
    structdef="StackstX509NAME"
    argtype="StackstX509NAME tag"
    rvtype="StackstX509NAME"/>

  <typedef name="ERRstringdatast"
    embed="embed"
    ponytypein="ERRstringdatast tag"
    ponytypeinconv=""
    ponytypeout="ERRstringdatast"
    structtype="ERRstringdatast"
    structdef="ERRstringdatast"
    argtype="ERRstringdatast tag"
    rvtype="ERRstringdatast"/>

  <typedef name="ASIdentifiersst"
    embed="embed"
    ponytypein="ASIdentifiersst tag"
    ponytypeinconv=""
    ponytypeout="ASIdentifiersst"
    structtype="ASIdentifiersst"
    structdef="ASIdentifiersst"
    argtype="ASIdentifiersst tag"
    rvtype="ASIdentifiersst"/>

  <typedef name="LhashstOPENSSLSTRING"
    embed="embed"
    ponytypein="LhashstOPENSSLSTRING tag"
    ponytypeinconv=""
    ponytypeout="LhashstOPENSSLSTRING"
    structtype="LhashstOPENSSLSTRING"
    structdef="LhashstOPENSSLSTRING"
    argtype="LhashstOPENSSLSTRING tag"
    rvtype="LhashstOPENSSLSTRING"/>

  <typedef name="ASN1ITEMst"
    embed="embed"
    ponytypein="ASN1ITEMst tag"
    ponytypeinconv=""
    ponytypeout="ASN1ITEMst"
    structtype="ASN1ITEMst"
    structdef="ASN1ITEMst"
    argtype="ASN1ITEMst tag"
    rvtype="ASN1ITEMst"/>

  <typedef name="Dhmethod"
    embed="embed"
    ponytypein="Dhmethod tag"
    ponytypeinconv=""
    ponytypeout="Dhmethod"
    structtype="Dhmethod"
    structdef="Dhmethod"
    argtype="Dhmethod tag"
    rvtype="Dhmethod"/>

  <typedef name="StackstASN1STRING"
    embed="embed"
    ponytypein="StackstASN1STRING tag"
    ponytypeinconv=""
    ponytypeout="StackstASN1STRING"
    structtype="StackstASN1STRING"
    structdef="StackstASN1STRING"
    argtype="StackstASN1STRING tag"
    rvtype="StackstASN1STRING"/>

  <typedef name="StackstX509REVOKED"
    embed="embed"
    ponytypein="StackstX509REVOKED tag"
    ponytypeinconv=""
    ponytypeout="StackstX509REVOKED"
    structtype="StackstX509REVOKED"
    structdef="StackstX509REVOKED"
    argtype="StackstX509REVOKED tag"
    rvtype="StackstX509REVOKED"/>

  <typedef name="NAMECONSTRAINTSst"
    embed="embed"
    ponytypein="NAMECONSTRAINTSst tag"
    ponytypeinconv=""
    ponytypeout="NAMECONSTRAINTSst"
    structtype="NAMECONSTRAINTSst"
    structdef="NAMECONSTRAINTSst"
    argtype="NAMECONSTRAINTSst tag"
    rvtype="NAMECONSTRAINTSst"/>

  <typedef name="Dhst"
    embed="embed"
    ponytypein="Dhst tag"
    ponytypeinconv=""
    ponytypeout="Dhst"
    structtype="Dhst"
    structdef="Dhst"
    argtype="Dhst tag"
    rvtype="Dhst"/>

  <typedef name="X509lookupst"
    embed="embed"
    ponytypein="X509lookupst tag"
    ponytypeinconv=""
    ponytypeout="X509lookupst"
    structtype="X509lookupst"
    structdef="X509lookupst"
    argtype="X509lookupst tag"
    rvtype="X509lookupst"/>

  <typedef name="Uist"
    embed="embed"
    ponytypein="Uist tag"
    ponytypeinconv=""
    ponytypeout="Uist"
    structtype="Uist"
    structdef="Uist"
    argtype="Uist tag"
    rvtype="Uist"/>

  <typedef name="Bfkeyst"
    embed="embed"
    ponytypein="Bfkeyst tag"
    ponytypeinconv=""
    ponytypeout="Bfkeyst"
    structtype="Bfkeyst"
    structdef="Bfkeyst"
    argtype="Bfkeyst tag"
    rvtype="Bfkeyst"/>

  <typedef name="X509Store"
    embed="embed"
    ponytypein="X509Store tag"
    ponytypeinconv=""
    ponytypeout="X509Store"
    structtype="X509Store"
    structdef="X509Store"
    argtype="X509Store tag"
    rvtype="X509Store"/>

  <typedef name="PBKDF2PARAMst"
    embed="embed"
    ponytypein="PBKDF2PARAMst tag"
    ponytypeinconv=""
    ponytypeout="PBKDF2PARAMst"
    structtype="PBKDF2PARAMst"
    structdef="PBKDF2PARAMst"
    argtype="PBKDF2PARAMst tag"
    rvtype="PBKDF2PARAMst"/>

  <typedef name="Asn1pctxst"
    embed="embed"
    ponytypein="Asn1pctxst tag"
    ponytypeinconv=""
    ponytypeout="Asn1pctxst"
    structtype="Asn1pctxst"
    structdef="Asn1pctxst"
    argtype="Asn1pctxst tag"
    rvtype="Asn1pctxst"/>

  <typedef name="Uimethodst"
    embed="embed"
    ponytypein="Uimethodst tag"
    ponytypeinconv=""
    ponytypeout="Uimethodst"
    structtype="Uimethodst"
    structdef="Uimethodst"
    argtype="Uimethodst tag"
    rvtype="Uimethodst"/>

  <typedef name="Ctpolicyevalctxst"
    embed="embed"
    ponytypein="Ctpolicyevalctxst tag"
    ponytypeinconv=""
    ponytypeout="Ctpolicyevalctxst"
    structtype="Ctpolicyevalctxst"
    structdef="Ctpolicyevalctxst"
    argtype="Ctpolicyevalctxst tag"
    rvtype="Ctpolicyevalctxst"/>

  <typedef name="StackstASN1GENERALSTRING"
    embed="embed"
    ponytypein="StackstASN1GENERALSTRING tag"
    ponytypeinconv=""
    ponytypeout="StackstASN1GENERALSTRING"
    structtype="StackstASN1GENERALSTRING"
    structdef="StackstASN1GENERALSTRING"
    argtype="StackstASN1GENERALSTRING tag"
    rvtype="StackstASN1GENERALSTRING"/>

  <typedef name="IPAddressRangest"
    embed="embed"
    ponytypein="IPAddressRangest tag"
    ponytypeinconv=""
    ponytypeout="IPAddressRangest"
    structtype="IPAddressRangest"
    structdef="IPAddressRangest"
    argtype="IPAddressRangest tag"
    rvtype="IPAddressRangest"/>

  <typedef name="Srtpprotectionprofilest"
    embed="embed"
    ponytypein="Srtpprotectionprofilest tag"
    ponytypeinconv=""
    ponytypeout="Srtpprotectionprofilest"
    structtype="Srtpprotectionprofilest"
    structdef="Srtpprotectionprofilest"
    argtype="Srtpprotectionprofilest tag"
    rvtype="Srtpprotectionprofilest"/>

  <typedef name="Asn1typest"
    embed="embed"
    ponytypein="Asn1typest tag"
    ponytypeinconv=""
    ponytypeout="Asn1typest"
    structtype="Asn1typest"
    structdef="Asn1typest"
    argtype="Asn1typest tag"
    rvtype="Asn1typest"/>

  <typedef name="Rsast"
    embed="embed"
    ponytypein="Rsast tag"
    ponytypeinconv=""
    ponytypeout="Rsast"
    structtype="Rsast"
    structdef="Rsast"
    argtype="Rsast tag"
    rvtype="Rsast"/>

  <typedef name="PKCS12st"
    embed="embed"
    ponytypein="PKCS12st tag"
    ponytypeinconv=""
    ponytypeout="PKCS12st"
    structtype="PKCS12st"
    structdef="PKCS12st"
    argtype="PKCS12st tag"
    rvtype="PKCS12st"/>

  <typedef name="StackstCONFVALUE"
    embed="embed"
    ponytypein="StackstCONFVALUE tag"
    ponytypeinconv=""
    ponytypeout="StackstCONFVALUE"
    structtype="StackstCONFVALUE"
    structdef="StackstCONFVALUE"
    argtype="StackstCONFVALUE tag"
    rvtype="StackstCONFVALUE"/>

  <typedef name="X509certauxst"
    embed="embed"
    ponytypein="X509certauxst tag"
    ponytypeinconv=""
    ponytypeout="X509certauxst"
    structtype="X509certauxst"
    structdef="X509certauxst"
    argtype="X509certauxst tag"
    rvtype="X509certauxst"/>

  <typedef name="CMSReceiptRequestst"
    embed="embed"
    ponytypein="CMSReceiptRequestst tag"
    ponytypeinconv=""
    ponytypeout="CMSReceiptRequestst"
    structtype="CMSReceiptRequestst"
    structdef="CMSReceiptRequestst"
    argtype="CMSReceiptRequestst tag"
    rvtype="CMSReceiptRequestst"/>

  <typedef name="PBEPARAMst"
    embed="embed"
    ponytypein="PBEPARAMst tag"
    ponytypeinconv=""
    ponytypeout="PBEPARAMst"
    structtype="PBEPARAMst"
    structdef="PBEPARAMst"
    argtype="PBEPARAMst tag"
    rvtype="PBEPARAMst"/>

  <typedef name="DESks"
    embed="embed"
    ponytypein="DESks tag"
    ponytypeinconv=""
    ponytypeout="DESks"
    structtype="DESks"
    structdef="DESks"
    argtype="DESks tag"
    rvtype="DESks"/>

  <typedef name="PBE2PARAMst"
    embed="embed"
    ponytypein="PBE2PARAMst tag"
    ponytypeinconv=""
    ponytypeout="PBE2PARAMst"
    structtype="PBE2PARAMst"
    structdef="PBE2PARAMst"
    argtype="PBE2PARAMst tag"
    rvtype="PBE2PARAMst"/>

  <typedef name="Compmethodst"
    embed="embed"
    ponytypein="Compmethodst tag"
    ponytypeinconv=""
    ponytypeout="Compmethodst"
    structtype="Compmethodst"
    structdef="Compmethodst"
    argtype="Compmethodst tag"
    rvtype="Compmethodst"/>

  <typedef name="Evpcipherinfost"
    embed="embed"
    ponytypein="Evpcipherinfost tag"
    ponytypeinconv=""
    ponytypeout="Evpcipherinfost"
    structtype="Evpcipherinfost"
    structdef="Evpcipherinfost"
    argtype="Evpcipherinfost tag"
    rvtype="Evpcipherinfost"/>

  <typedef name="Ocsprespbytesst"
    embed="embed"
    ponytypein="Ocsprespbytesst tag"
    ponytypeinconv=""
    ponytypeout="Ocsprespbytesst"
    structtype="Ocsprespbytesst"
    structdef="Ocsprespbytesst"
    argtype="Ocsprespbytesst tag"
    rvtype="Ocsprespbytesst"/>

  <typedef name="ASN1String"
    embed="embed"
    ponytypein="ASN1String tag"
    ponytypeinconv=""
    ponytypeout="ASN1String val"
    structtype="ASN1String"
    structdef="ASN1String"
    argtype="ASN1String tag"
    rvtype="ASN1String val"/>

  <typedef name="StackstX509ATTRIBUTE"
    embed="embed"
    ponytypein="StackstX509ATTRIBUTE tag"
    ponytypeinconv=""
    ponytypeout="StackstX509ATTRIBUTE"
    structtype="StackstX509ATTRIBUTE"
    structdef="StackstX509ATTRIBUTE"
    argtype="StackstX509ATTRIBUTE tag"
    rvtype="StackstX509ATTRIBUTE"/>

  <typedef name="CMSOtherKeyAttributest"
    embed="embed"
    ponytypein="CMSOtherKeyAttributest tag"
    ponytypeinconv=""
    ponytypeout="CMSOtherKeyAttributest"
    structtype="CMSOtherKeyAttributest"
    structdef="CMSOtherKeyAttributest"
    argtype="CMSOtherKeyAttributest tag"
    rvtype="CMSOtherKeyAttributest"/>

  <typedef name="Valisttag"
    embed="embed"
    ponytypein="Valisttag tag"
    ponytypeinconv=""
    ponytypeout="Valisttag"
    structtype="Valisttag"
    structdef="Valisttag"
    argtype="Valisttag tag"
    rvtype="Valisttag"/>

  <typedef name="Evpmdst"
    embed="embed"
    ponytypein="EVPMD tag"
    ponytypeinconv=""
    ponytypeout="EVPMD"
    structtype="EVPMD"
    structdef="EVPMD"
    argtype="EVPMD tag"
    rvtype="EVPMD"/>

  <typedef name="Bnrecpctxst"
    embed="embed"
    ponytypein="Bnrecpctxst tag"
    ponytypeinconv=""
    ponytypeout="Bnrecpctxst"
    structtype="Bnrecpctxst"
    structdef="Bnrecpctxst"
    argtype="Bnrecpctxst tag"
    rvtype="Bnrecpctxst"/>

  <typedef name="StackstPROFESSIONINFO"
    embed="embed"
    ponytypein="StackstPROFESSIONINFO tag"
    ponytypeinconv=""
    ponytypeout="StackstPROFESSIONINFO"
    structtype="StackstPROFESSIONINFO"
    structdef="StackstPROFESSIONINFO"
    argtype="StackstPROFESSIONINFO tag"
    rvtype="StackstPROFESSIONINFO"/>

  <typedef name="Pkcs7recipinfost"
    embed="embed"
    ponytypein="Pkcs7recipinfost tag"
    ponytypeinconv=""
    ponytypeout="Pkcs7recipinfost"
    structtype="Pkcs7recipinfost"
    structdef="Pkcs7recipinfost"
    argtype="Pkcs7recipinfost tag"
    rvtype="Pkcs7recipinfost"/>

  <typedef name="Osslstorectxst"
    embed="embed"
    ponytypein="Osslstorectxst tag"
    ponytypeinconv=""
    ponytypeout="Osslstorectxst"
    structtype="Osslstorectxst"
    structdef="Osslstorectxst"
    argtype="Osslstorectxst tag"
    rvtype="Osslstorectxst"/>

  <typedef name="Ocspsingleresponsest"
    embed="embed"
    ponytypein="Ocspsingleresponsest tag"
    ponytypeinconv=""
    ponytypeout="Ocspsingleresponsest"
    structtype="Ocspsingleresponsest"
    structdef="Ocspsingleresponsest"
    argtype="Ocspsingleresponsest tag"
    rvtype="Ocspsingleresponsest"/>

  <typedef name="StackstX509EXTENSION"
    embed="embed"
    ponytypein="StackX509Extension tag"
    ponytypeinconv=""
    ponytypeout="StackX509Extension"
    structtype="StackX509Extension"
    structdef="StackX509Extension"
    argtype="StackX509Extension tag"
    rvtype="StackX509Extension"/>

  <typedef name="X509"
    embed="embed"
    ponytypein="X509 tag"
    ponytypeinconv=""
    ponytypeout="X509"
    structtype="X509"
    structdef="X509"
    argtype="X509 tag"
    rvtype="X509"/>

  <typedef name="U64"
    embed="var"
    ponytypein="U64"
    ponytypeinconv=""
    ponytypeout="U64"
    structtype="U64"
    structdef="U64(0)"
    argtype="U64"
    rvtype="U64"/>

  <typedef name="Tm"
    embed="embed"
    ponytypein="Tm tag"
    ponytypeinconv=""
    ponytypeout="Tm"
    structtype="Tm"
    structdef="Tm"
    argtype="Tm tag"
    rvtype="Tm"/>

  <typedef name="POLICYINFOst"
    embed="embed"
    ponytypein="POLICYINFOst tag"
    ponytypeinconv=""
    ponytypeout="POLICYINFOst"
    structtype="POLICYINFOst"
    structdef="POLICYINFOst"
    argtype="POLICYINFOst tag"
    rvtype="POLICYINFOst"/>

  <typedef name="OtherNamest"
    embed="embed"
    ponytypein="OtherNamest tag"
    ponytypeinconv=""
    ponytypeout="OtherNamest"
    structtype="OtherNamest"
    structdef="OtherNamest"
    argtype="OtherNamest tag"
    rvtype="OtherNamest"/>

  <typedef name="X509extensionst"
    embed="embed"
    ponytypein="X509Extension tag"
    ponytypeinconv=""
    ponytypeout="X509Extension"
    structtype="X509Extension"
    structdef="X509Extension"
    argtype="X509Extension tag"
    rvtype="X509Extension"/>

  <typedef name="Evppkeyst"
    embed="embed"
    ponytypein="Evppkeyst tag"
    ponytypeinconv=""
    ponytypeout="Evppkeyst"
    structtype="Evppkeyst"
    structdef="Evppkeyst"
    argtype="Evppkeyst tag"
    rvtype="Evppkeyst"/>

  <typedef name="StackstX509INFO"
    embed="embed"
    ponytypein="StackstX509INFO tag"
    ponytypeinconv=""
    ponytypeout="StackstX509INFO"
    structtype="StackstX509INFO"
    structdef="StackstX509INFO"
    argtype="StackstX509INFO tag"
    rvtype="StackstX509INFO"/>

  <typedef name="X509crlmethodst"
    embed="embed"
    ponytypein="X509crlmethodst tag"
    ponytypeinconv=""
    ponytypeout="X509crlmethodst"
    structtype="X509crlmethodst"
    structdef="X509crlmethodst"
    argtype="X509crlmethodst tag"
    rvtype="X509crlmethodst"/>

  <typedef name="X509revokedst"
    embed="embed"
    ponytypein="X509revokedst tag"
    ponytypeinconv=""
    ponytypeout="X509revokedst"
    structtype="X509revokedst"
    structdef="X509revokedst"
    argtype="X509revokedst tag"
    rvtype="X509revokedst"/>

  <typedef name="Ocsponerequestst"
    embed="embed"
    ponytypein="Ocsponerequestst tag"
    ponytypeinconv=""
    ponytypeout="Ocsponerequestst"
    structtype="Ocsponerequestst"
    structdef="Ocsponerequestst"
    argtype="Ocsponerequestst tag"
    rvtype="Ocsponerequestst"/>

  <typedef name="StackstOPENSSLSTRING"
    embed="embed"
    ponytypein="StackstOPENSSLSTRING tag"
    ponytypeinconv=""
    ponytypeout="StackstOPENSSLSTRING"
    structtype="StackstOPENSSLSTRING"
    structdef="StackstOPENSSLSTRING"
    argtype="StackstOPENSSLSTRING tag"
    rvtype="StackstOPENSSLSTRING"/>

  <typedef name="StackstOCSPONEREQ"
    embed="embed"
    ponytypein="StackstOCSPONEREQ tag"
    ponytypeinconv=""
    ponytypeout="StackstOCSPONEREQ"
    structtype="StackstOCSPONEREQ"
    structdef="StackstOCSPONEREQ"
    argtype="StackstOCSPONEREQ tag"
    rvtype="StackstOCSPONEREQ"/>

  <typedef name="StackstIPAddressFamily"
    embed="embed"
    ponytypein="StackstIPAddressFamily tag"
    ponytypeinconv=""
    ponytypeout="StackstIPAddressFamily"
    structtype="StackstIPAddressFamily"
    structdef="StackstIPAddressFamily"
    argtype="StackstIPAddressFamily tag"
    rvtype="StackstIPAddressFamily"/>

  <typedef name="X509reqst"
    embed="embed"
    ponytypein="X509reqst tag"
    ponytypeinconv=""
    ponytypeout="X509reqst"
    structtype="X509reqst"
    structdef="X509reqst"
    argtype="X509reqst tag"
    rvtype="X509reqst"/>

  <typedef name="Rc4keyst"
    embed="embed"
    ponytypein="Rc4keyst tag"
    ponytypeinconv=""
    ponytypeout="Rc4keyst"
    structtype="Rc4keyst"
    structdef="Rc4keyst"
    argtype="Rc4keyst tag"
    rvtype="Rc4keyst"/>

  <typedef name="StackstCMSRevocationInfoChoice"
    embed="embed"
    ponytypein="StackstCMSRevocationInfoChoice tag"
    ponytypeinconv=""
    ponytypeout="StackstCMSRevocationInfoChoice"
    structtype="StackstCMSRevocationInfoChoice"
    structdef="StackstCMSRevocationInfoChoice"
    argtype="StackstCMSRevocationInfoChoice tag"
    rvtype="StackstCMSRevocationInfoChoice"/>

  <typedef name="X509cinfst"
    embed="embed"
    ponytypein="X509cinfst tag"
    ponytypeinconv=""
    ponytypeout="X509cinfst"
    structtype="X509cinfst"
    structdef="X509cinfst"
    argtype="X509cinfst tag"
    rvtype="X509cinfst"/>

  <typedef name="StackstASN1STRINGTABLE"
    embed="embed"
    ponytypein="StackstASN1STRINGTABLE tag"
    ponytypeinconv=""
    ponytypeout="StackstASN1STRINGTABLE"
    structtype="StackstASN1STRINGTABLE"
    structdef="StackstASN1STRINGTABLE"
    argtype="StackstASN1STRINGTABLE tag"
    rvtype="StackstASN1STRINGTABLE"/>

  <typedef name="Ecparametersst"
    embed="embed"
    ponytypein="Ecparametersst tag"
    ponytypeinconv=""
    ponytypeout="Ecparametersst"
    structtype="Ecparametersst"
    structdef="Ecparametersst"
    argtype="Ecparametersst tag"
    rvtype="Ecparametersst"/>

  <typedef name="Ocspcrlidst"
    embed="embed"
    ponytypein="Ocspcrlidst tag"
    ponytypeinconv=""
    ponytypeout="Ocspcrlidst"
    structtype="Ocspcrlidst"
    structdef="Ocspcrlidst"
    argtype="Ocspcrlidst tag"
    rvtype="Ocspcrlidst"/>

  <typedef name="StackstCMSRecipientInfo"
    embed="embed"
    ponytypein="StackstCMSRecipientInfo tag"
    ponytypeinconv=""
    ponytypeout="StackstCMSRecipientInfo"
    structtype="StackstCMSRecipientInfo"
    structdef="StackstCMSRecipientInfo"
    argtype="StackstCMSRecipientInfo tag"
    rvtype="StackstCMSRecipientInfo"/>

  <typedef name="StackstX509NAMEENTRY"
    embed="embed"
    ponytypein="StackstX509NAMEENTRY tag"
    ponytypeinconv=""
    ponytypeout="StackstX509NAMEENTRY"
    structtype="StackstX509NAMEENTRY"
    structdef="StackstX509NAMEENTRY"
    argtype="StackstX509NAMEENTRY tag"
    rvtype="StackstX509NAMEENTRY"/>

  <typedef name="ASRangest"
    embed="embed"
    ponytypein="ASRangest tag"
    ponytypeinconv=""
    ponytypeout="ASRangest"
    structtype="ASRangest"
    structdef="ASRangest"
    argtype="ASRangest tag"
    rvtype="ASRangest"/>

  <typedef name="Sslst"
    embed="embed"
    ponytypein="Sslst tag"
    ponytypeinconv=""
    ponytypeout="Sslst"
    structtype="Sslst"
    structdef="Sslst"
    argtype="Sslst tag"
    rvtype="Sslst"/>

  <typedef name="Pkcs7signedandenvelopedst"
    embed="embed"
    ponytypein="Pkcs7signedandenvelopedst tag"
    ponytypeinconv=""
    ponytypeout="Pkcs7signedandenvelopedst"
    structtype="Pkcs7signedandenvelopedst"
    structdef="Pkcs7signedandenvelopedst"
    argtype="Pkcs7signedandenvelopedst tag"
    rvtype="Pkcs7signedandenvelopedst"/>

  <typedef name="Osslinitsettingsst"
    embed="embed"
    ponytypein="Osslinitsettingsst tag"
    ponytypeinconv=""
    ponytypeout="Osslinitsettingsst"
    structtype="Osslinitsettingsst"
    structdef="Osslinitsettingsst"
    argtype="Osslinitsettingsst tag"
    rvtype="Osslinitsettingsst"/>

  <typedef name="Ocspresponsedatast"
    embed="embed"
    ponytypein="Ocspresponsedatast tag"
    ponytypeinconv=""
    ponytypeout="Ocspresponsedatast"
    structtype="Ocspresponsedatast"
    structdef="Ocspresponsedatast"
    argtype="Ocspresponsedatast tag"
    rvtype="Ocspresponsedatast"/>

  <typedef name="X509Name"
    embed="embed"
    ponytypein="X509Name tag"
    ponytypeinconv=""
    ponytypeout="X509Name"
    structtype="X509Name"
    structdef="X509Name"
    argtype="X509Name tag"
    rvtype="X509Name"/>

  <typedef name="IPAddressFamilyst"
    embed="embed"
    ponytypein="IPAddressFamilyst tag"
    ponytypeinconv=""
    ponytypeout="IPAddressFamilyst"
    structtype="IPAddressFamilyst"
    structdef="IPAddressFamilyst"
    argtype="IPAddressFamilyst tag"
    rvtype="IPAddressFamilyst"/>

  <typedef name="U8"
    embed="var"
    ponytypein="U8"
    ponytypeinconv=""
    ponytypeout="U8"
    structtype="U8"
    structdef="U8(0)"
    argtype="U8"
    rvtype="U8"/>

  <typedef name="NOTICEREFst"
    embed="embed"
    ponytypein="NOTICEREFst tag"
    ponytypeinconv=""
    ponytypeout="NOTICEREFst"
    structtype="NOTICEREFst"
    structdef="NOTICEREFst"
    argtype="NOTICEREFst tag"
    rvtype="NOTICEREFst"/>

  <typedef name="SHA512statest"
    embed="embed"
    ponytypein="SHA512statest tag"
    ponytypeinconv=""
    ponytypeout="SHA512statest"
    structtype="SHA512statest"
    structdef="SHA512statest"
    argtype="SHA512statest tag"
    rvtype="SHA512statest"/>

  <typedef name="Admissionsst"
    embed="embed"
    ponytypein="Admissionsst tag"
    ponytypeinconv=""
    ponytypeout="Admissionsst"
    structtype="Admissionsst"
    structdef="Admissionsst"
    argtype="Admissionsst tag"
    rvtype="Admissionsst"/>

  <typedef name="Confst"
    embed="embed"
    ponytypein="Confst tag"
    ponytypeinconv=""
    ponytypeout="Confst"
    structtype="Confst"
    structdef="Confst"
    argtype="Confst tag"
    rvtype="Confst"/>

  <typedef name="StackstX509CRL"
    embed="embed"
    ponytypein="StackstX509CRL tag"
    ponytypeinconv=""
    ponytypeout="StackstX509CRL"
    structtype="StackstX509CRL"
    structdef="StackstX509CRL"
    argtype="StackstX509CRL tag"
    rvtype="StackstX509CRL"/>

  <typedef name="Lhashst"
    embed="embed"
    ponytypein="Lhashst tag"
    ponytypeinconv=""
    ponytypeout="Lhashst"
    structtype="Lhashst"
    structdef="Lhashst"
    argtype="Lhashst tag"
    rvtype="Lhashst"/>

  <typedef name="POLICYQUALINFOst"
    embed="embed"
    ponytypein="POLICYQUALINFOst tag"
    ponytypeinconv=""
    ponytypeout="POLICYQUALINFOst"
    structtype="POLICYQUALINFOst"
    structdef="POLICYQUALINFOst"
    argtype="POLICYQUALINFOst tag"
    rvtype="POLICYQUALINFOst"/>
</typedefs>

