<?xml version="1.0" encoding="UTF-8"?>
<castxml2pony xmlns:xi="http://www.w3.org/2001/XInclude">
<xi:include href="../usetypes.xml"/>
<xi:include href="../use.xml"/>
<xi:include href="../../../castxml-results/gtk-3.xml"/>
<inherits>
  <inherit name="GObject" ponyfn="gobject" path="misc.widget.parent_instance"/>
  <inherit name="GtkWidget" ponyfn="gtkwidget" path="misc.widget"/>
  <inherit name="GtkMisc" ponyfn="gtkmisc" path="misc"/>
</inherits>
<renders>
  <renderuse name="gtk_label_get_type" render="1"/>
  <renderuse name="gtk_label_new" render="1"/>
  <renderuse name="gtk_label_new_with_mnemonic" render="1"/>
  <renderuse name="gtk_label_set_text" render="1"/>
  <renderuse name="gtk_label_get_text" render="1"/>
  <renderuse name="gtk_label_set_attributes" render="1"/>
  <renderuse name="gtk_label_get_attributes" render="1"/>
  <renderuse name="gtk_label_set_label" render="1"/>
  <renderuse name="gtk_label_get_label" render="1"/>
  <renderuse name="gtk_label_set_markup" render="1"/>
  <renderuse name="gtk_label_set_use_markup" render="1"/>
  <renderuse name="gtk_label_get_use_markup" render="1"/>
  <renderuse name="gtk_label_set_use_underline" render="1"/>
  <renderuse name="gtk_label_get_use_underline" render="1"/>
  <renderuse name="gtk_label_set_markup_with_mnemonic" render="1"/>
  <renderuse name="gtk_label_get_mnemonic_keyval" render="1"/>
  <renderuse name="gtk_label_set_mnemonic_widget" render="1"/>
  <renderuse name="gtk_label_get_mnemonic_widget" render="1"/>
  <renderuse name="gtk_label_set_text_with_mnemonic" render="1"/>
  <renderuse name="gtk_label_set_justify" render="1"/>
  <renderuse name="gtk_label_get_justify" render="1"/>
  <renderuse name="gtk_label_set_ellipsize" render="1"/>
  <renderuse name="gtk_label_get_ellipsize" render="1"/>
  <renderuse name="gtk_label_set_width_chars" render="1"/>
  <renderuse name="gtk_label_get_width_chars" render="1"/>
  <renderuse name="gtk_label_set_max_width_chars" render="1"/>
  <renderuse name="gtk_label_get_max_width_chars" render="1"/>
  <renderuse name="gtk_label_set_lines" render="1"/>
  <renderuse name="gtk_label_get_lines" render="1"/>
  <renderuse name="gtk_label_set_pattern" render="1"/>
  <renderuse name="gtk_label_set_line_wrap" render="1"/>
  <renderuse name="gtk_label_get_line_wrap" render="1"/>
  <renderuse name="gtk_label_set_line_wrap_mode" render="1"/>
  <renderuse name="gtk_label_get_line_wrap_mode" render="1"/>
  <renderuse name="gtk_label_set_selectable" render="1"/>
  <renderuse name="gtk_label_get_selectable" render="1"/>
  <renderuse name="gtk_label_set_angle" render="1"/>
  <renderuse name="gtk_label_get_angle" render="1"/>
  <renderuse name="gtk_label_select_region" render="1"/>
  <renderuse name="gtk_label_get_selection_bounds" render="1"/>
  <renderuse name="gtk_label_get_layout" render="1"/>
  <renderuse name="gtk_label_get_layout_offsets" render="1"/>
  <renderuse name="gtk_label_set_single_line_mode" render="1"/>
  <renderuse name="gtk_label_get_single_line_mode" render="1"/>
  <renderuse name="gtk_label_get_current_uri" render="1"/>
  <renderuse name="gtk_label_set_track_visited_links" render="1"/>
  <renderuse name="gtk_label_get_track_visited_links" render="1"/>
  <renderuse name="gtk_label_set_xalign" render="1"/>
  <renderuse name="gtk_label_get_xalign" render="1"/>
  <renderuse name="gtk_label_set_yalign" render="1"/>
  <renderuse name="gtk_label_get_yalign" render="1"/>
</renders>
</castxml2pony>
